Workbook

Sheet DATA
A1: Ubicación | B1: Parte o Producto de la especie objeto de manejo sostenible | C1: Unidad de medida del producto | D1: Método de recolección | E1: Frecuencia de recolección | F1: Recursos humanos por tiempo empleados para la cosecha | G1: Objeto de manejo sostenible Si/No | H1: Tipo de corteza | I1: Fracción de la copa medida | J1: Tipos de exudados | K1: Categorías de amenaza:
A2: Norte | B2: Raíz | C2: Kilogramos (Kg) | D2: Manual | E2: Anual | F2: Cosechadores | G2: Si | H2: Muerta | I2: 1 | J2: Látex | K2: Datos Insuficientes (DD)
A3: Sur | B3: Cogollos | C3: Toneladas (Ton) | D3: Mecanico | E3: Semestral | F3: Transportadores | G3: No | H3: Viva | I3: 0.5 | J3: Aceites | K3: Preocupación Menor (LC)
B4: Corteza | C4: Litro (L) | E4: Mensual | F4: Guía | I4: 0.25 | J4: Resinas | K4: Casi Amenazado (NT)
B5: Hojas | C5: Mililiros (mm) | E5: Diario | F5: Otros | I5: 0.125 | J5: Gomas | K5: Vulnerable (VU)
A6: Tipo de documentos: | B6: Flores | C6: Centímetro cúbico (cc) | E6: Eventual | I6: 0.0625 | J6: Otros | K6: En Peligro (EN)
A7: Cédula de ciudadanía | B7: Exudado | C7: Metros cubicos (m3) | K7: En Peligro Crítico (CR)
A8: Cédula de Extranjería | B8: Frutos | C8: Gramos (g) | K8: Extinto en Estado Silvestre (EW)
A9: NIT | B9: Semillas | C9: Número (#) | K9: Extinto (EX)
B10: Lianas o Bejucos | E10: Meses | F10: Régimen de propiedad | G10: Unidades de área: | K10: No Evaluado (NE)
B11: Plántulas | E11: Enero | F11: Propiedad privada | G11: Hectáreas | H11: ha | K11: Sin amenaza
E12: Febrero | F12: Público: Baldio de la Nación | G12: Metros cuadrados | H12: m2
A13: Departamentos | B13: Municipios | C13: Hábito | E13: Marzo | F13: Propiedad colectiva
A14: Amazonas | B14: Florencia | C14: Árbol | E14: Abril | K14: Estado físico
A15: Caquetá | B15: Albania | C15: Arbusto | E15: Mayo | K15: Tallo recto vertical
A16: Putumayo | B16: Belén de los Andaquíes | C16: Hierba terrestre | E16: Junio | K16: Inclinado o sinuoso
B17: Cartagena del Chairá | C17: Epífita | E17: Julio | F17: Calidad del interesado: | K17: Ligeramente torcido
B18: Curillo | C18: Bejuco/liana | E18: Agosto | F18: Propietario | K18: Muy torcido
B19: El Doncello | C19: Hemiepífita | E19: Septiembre | F19: Poseedor de propiedad privada declarado como propietario de predio privado
B20: El Paujíl | C20: Palma | E20: Octubre | F20: Ocupante
B21: La Montañita | E21: Noviembre | F21: Tenedor | K21: Estado sanitario de los individuos
B22: Milán | E22: Diciembre | F22: Autorizado | K22: Bueno - sin afectaciones
B23: Morelia | C23: Tipo de transporte | F23: Ente Territorial | K23: Señales de pudrición
B24: Puerto Rico | C24: Terretre | F24: Consejo Comunitario | K24: Presencia de hongos
B25: San José del Fragua | C25: Fluvial | F25: Resguardo Indígena | K25: Termitas
B26: San Vicente del Caguán | C26: Áereo | F26: Otro | K26: Hormigas
B27: Solano | K27: Parásitas
B28: Solita | K28: Otra enfermedad o plaga
B29: Valparaíso | C29: Modo de adquirir derecho: | F29: Recurso hídrico: | G29: Vedas:
B30: Mocoa | F30: Río | G30: No aplica | K30: Formas parcelas muestreo
B31: Colón | C31: Predios de propiedad privada o colectiva | F31: Quebrada | G31: Res. 0110/2015 Corpoamazonia | K31: Cuadrada
B32: Orito | C32: Autorización | F32: Arroyo | G32: Res. 1602/1995 Minambiente | K32: Rectangular
B33: Puerto Asís | F33: Lago natural | G33: Res. 213/1977 Inderena | K33: Transecto
B34: Puerto Caicedo | C34: Terrenos de dominio público: | F34: Humedal | G34: Res. 316/1974 Inderena | K34: Circular
B35: Puerto Guzmán | C35: Permiso | G35: Res. 801/1977 Inderena
B36: Puerto Leguízamo | C36: Asociación
B37: Sibundoy | C37: Concesión
B38: San Francisco
B39: San Miguel
B40: Santiago
B41: Valle del Guamuez
B42: Villagarzón
B43: Leticia
B44: El Encanto
B45: La Chorrera
B46: La Pedrera
B47: La Victoria
B48: Mirití - Paraná
B49: Puerto Alegría
... B53: Tarapacá

Sheet Datos_básicos 
F2: Formato para presentación de Informe de Censo o Inventario para Manejo Sostenible de Especies con Protocolo
F3: Corporación para el Desarrollo Sostenible del sur de la Amazonia
F4: Datos básicos de la solicitud del trámite
F5: Código: F-LAR-072 | R5: Versión: 2.0 | AG5: Fecha: 08/05/2025
B7: TIPO DE SOLICITUD: | I7: Nueva | L7: X | N7: Prórroga | S7: Modificación: | Z7: Número del expediente
B8: MODO A ADQUIRIR DERECHO: | L8: Predios de propiedad privada o colectiva: | X8: Autorización | AC8: Terrenos de dominio público:
B10: 1. INFORMACION DEL(OS) INTERESADO(S):
B11: Tipo de persona: | H11: Natural | K11: X | N11: Jurídica Privada | X11: Jurídica Pública (entidad del Estado):
B12: Nombre completo del interesado 1:
B13: Tipo de documento de identificación: | N13: Cédula de ciudadanía | V13: Número de identificación:
B14: Dirección: | Z14: Barrio/Vereda:
B15: Municipio: | F15: Florencia | Z15: Departamento: | AF15: Caquetá
B16: Teléfono/celular: | S16: Correo electrónico:
B17: Calidad del interesado en el trámite, sobre el predio: | T17: Seleccione una opción: | AC17: Otro
B18: Si indicó que la calidad del interesado es otro, especifique, cual otro:
B19: Nombre completo del interesado 2:
B20: Tipo de documento de identificación: | V20: Número de identificación:
B21: Dirección: | Z21: Barrio/Vereda:
B22: Municipio: | Z22: Departamento:
B23: Teléfono/celular: | S23: Correo electrónico:
B24: Nombre del Apoderado (Sólo si aplica):
B25: Tipo de documento de identificación: | V25: Número de identificación:
B26: Dirección: | Z26: Barrio/Vereda:
B27: Municipio: | Z27: Departamento:
B28: Teléfono/celular: | S28: Correo electrónico:
B29: No. de Tarjeta Profesional (si aplica):
B30: 2. INFORMACIÓN DEL PREDIO (en caso que la solicitud incluya varios predios, diligencie un archivo por cada predio):
B31: Nombre del predio:
B32: Dirección del predio - vereda: | Z32: Corregimiento:
B33: Municipio: | F33: Morelia | Z33: Departamento: | AF33: Caquetá
B34: Superficie o área total del predio (ha): | V34: Situacion legal del predio:
B35: En caso de propiedad privada, diligencie: | N35: Matricula Inmobiliaria: | AD35: Cédula Catastral:
B36: Uso actual del predio y área. El área se debe especificar en metros cuadrados (m2):
B37: Bosque primario: | H37: Si | J37: Especifique el área en m2 | V37: Bosque secundario | AC37: No | AE37: Especifique el área en m2
B38: Rastrojo alto: | H38: No | J38: Especifique el área en m2 | V38: Rastrojo bajo: | AC38: No | AE38: Especifique el área en m2
B39: Sistema agroforestal: | H39: No | J39: Especifique el área en m2 | V39: Sistema silvopastoril: | AC39: No | AE39: Especifique el área en m2
B40: Cultivos: | H40: No | J40: Especifique el área en m2 | V40: Potreros: | AC40: Si | AE40: Especifique el área en m2
B41: Otos usos: | H41: No | J41: Especifique el área en m2 | V41: Diga cuáles otros:
B42: Recuros hidricos existentes al interior o colindando con el predio: | V42: Seleccione una opción según sea el caso y dé el nombre, si existe:
B43: Río | E43: No | F43: Quebrada | J43: Si | L43: Arroyo | P43: No | R43: Humedal | V43: Si | X43: Otro | AD43: No | AF43: Nombre:
B44: Vias de acceso al predio: | J44: Carretera | N44: Si | P44: Camino veredal | V44: Si | X44: Trocha | AD44: Si | AF44: Río o fuente hídrica | AL44: No | AN44: N/A
B45: Otro - mencione cual via:
B46: Colindantes:
B47: Norte: | V47: Sur:
B48: Este: | V48: Oeste:
B49: Localización Geográfica del Predio:
B50: En el archivo denominado: "F-LAR-071 Plantilla para Coordenadas Geográficas” diligencie los datos de cada uno de los vértices del predio, en la hoja Coordenadas_POLIGONOS_LINEAS tal como se indica en ese formato.
B51: 3. INFORMACIÓN DE LA UNIDAD DE MANEJO FORESTAL (UMF) (en caso que en el predio haya 2 o más UMF agregue las filas que sean necesarias; en el caso de varios predios diligencie un archivo por predio):
B52: Nombre de la UMF: | AD52: Area de la UMF: | AN52: ha
B53: Tipos de ecosistema presentes en la UMF:
B54: Ecosistemas terrestres naturales: | M54: Bosque | P54: Si | R54: Sabana | V54: No | X54: Humedal | AB54: No | AD54: Bajo inundable | AJ54: No | AL54: Páramo | AN54: No
B55: Ecosistemas terrestres transformados: | N55: Bosque fragmentado | U55: No | W55: Vegetación secundaria | AF55: No | AH55: Agrosistemas o potreros | AN55: No
B56: Ecosistemas acuáticos naturales: | M56: Lóticos - aguas con corriente | W56: No | Y56: Lénticos - aguas estancadas o semiestancadas | AN56: No
B57: Tipo de bosque: | H57: Bosque de montaña | N57: No | P57: Bosque de tierra firme | Y57: Si | AA57: Bosque inundable | AH57: No | AJ57: N/A
B58: Cobertura vegetal: | I58: Bosque primario | N58: Si | P58: Bosque secundario | W58: No | Y58: Rastrojo alto | AD58: No | AF58: Rastrojo bajo | AK58: No | AM58: N/A
B59: Tierras cultivadas o agroecosistemas | N59: No | P59: Pastizales | W59: No | Y59: Humedal | AD59: No | AF59: Cananguchal | AK59: No | AM59: Asaisal | AN59: No
B60: Plantaciones forestales | I60: No | K60: Otra - cual: | N60: No
B61: Principales especies forestales existentes en la UMF:
B63: Localización Geográfica de la UMF:
B64: En el archivo: F-LAR-071 Plantilla para Coordenadas Geográficas diligencie los datos de cada uno de los vértices de la UMF, en la hoja Coordenadas_POLÍGONOS_LINEAS, tal como se indica en ese formato. En esa misma plantilla diligencie las coordenadas de los vértices de las áreas o parcelas de muestreo. La información diligenciada en este formato se deberá cargar posteriormente en el FUNL en VITAL.
B65: 4. MAPAS (en caso de varios predios diligencie un archivo por cada predio).
B66: En la hoja de este archivo denominada "Mapas" incluya el plano o mapa de localización geográfica del predio, de la(s) UMF(s), así como de las áreas o parcelas de muestreo de los individuos forestales objeto de manejo sostenible. En el caso de medianos y grandes usuarios, de acuerdo con la Resolución 219 de 2025, adicionalmente se debe entregar la cartografía en medio digital así como el shapefile.
B67: 5. INFORMACION DE LAS ESPECIES FORESTALES OBJETO DE MANEJO SOSTENIBLE:
B68: En la hoja adjunta denominada "Información_Especies" diligencie la información solicitada para cada una de las especies de interés.
B69: 6. REGISTRO FOTOGRAFICO:
B70: En la hoja adjunta denominada: "Registro fotográfico_Especies" agregue el registro fotográfico de todas las especies objeto de manejo sostenible. Incluya, de ser posible, como mínimo: planta completa, detalle de las hojas u otra(s) parte(s) clave para diferenciar la especie, parte a cosechar, flores y frutos. En la misma hoja agregue las secciones hasta completar los registros de todas las especie de interés.
B71: 7. INFORMACION ESPECÍFICA DE LOS INDIVIDUOS FORESTALES O DE LOS RECURSOS DE LA FLORA SILVESTRE, Y DE LOS PRODUCTOS FORESTALES NO MADERABLES (PFNM) DE INTERÉS
B72: En las hojas adjuntas denominadas: “Regis_Datos_” diligencie la información solicitada en cada campo según el PFNM o los recursos de la Flora silvestre a cosechar. Se debe diligenciar una hoja por cada tipo de producto. Si de varias especies se obtendrán el mismo producto, entonces diligencie la información de todas las especies en la misma hoja.
B73: 8. DETERMINACION DEL VOLUMEN DE PRODUCTOS FORESTALES NO MADERABLES A COSECHAR:
... B80: Nombre de quien diligencia la información del estudio técnico:
B81: Teléfono de contacto: | Q81: Correo electrónico:

Sheet Mapas
D2: Formato para presentación de Informe de Censo o Inventario para Manejo Sostenible de Especies con Protocolo
D3: Corporación para el Desarrollo Sostenible del sur de la Amazonia
D4: Planos o Mapas del Predio, de la(s) UMF, y de los individuos objeto de aprovechamiento
D5: Código: F-LAR-072 | G5: Versión: 2.0 | K5: Fecha: 08/05/2025
B7: PLANO DE LOCALIZACION GEOGRÁFICA DEL PREDIO DONDE SE UBICAN LAS AREAS OBJETO DE MANEJO SOSTENIBLE DE PFNM
B8: Nombre del predio: | E8: ='Datos_básicos '!I31 -> 0
B9: Vereda: | D9: ='Datos_básicos '!L32 -> 0 | G9: Municipio: | H9: ='Datos_básicos '!F33 -> Morelia | K9: Departamento: | M9: ='Datos_básicos '!AF33 -> Caquetá
B37: PLANO O MAPA DEL PREDIO Y DE LA UNIDAD O UNIDADES DE MANEJO FORESTAL (UMF) AL INTERIOR DEL PREDIO
B38: Nombre de la Unidad de Manejo Forestal: | G38: UMF
B39: Nombre del predio: | G39: ='Datos_básicos '!I31 -> 0
B40: Área total de la UMF (ha)
B68: PLANO O MAPA DE LOCALIZACION DE LOS INDIVIDUOS OBJETO DE MANEJO SOSTENIBLE
B69: Nombre de la Unidad de Manejo Forestal: | G69: UMF
B70: Nombre del predio: | G70: ='Datos_básicos '!I31 -> 0
B71: Área total de la UMF (ha)

Sheet Regis_Datos_Frutos_Semill_Leños
F2: Formato para presentación de Informe de Censo o Inventario para Manejo Sostenible de Especies con Protocolo
F3: Corporación para el Desarrollo Sostenible del sur de la Amazonia
F4: Plantilla para el registro de datos de campo de PFNM a aprovechar en árboles, arbolitos o árbustos (especies leñosas)
F5: Código: F-LAR-072 | H5: Versión: 2.0 | K5: Fecha: 08/05/2025
D7: Método de muestreo de individuos a aprovechar: | G7: Censo | H7: X | I7: Inventario Estadistico | L7: Area de Muestreo No. | O7: Forma | Q7: Largo (m) | S7: Ancho (m) | U7: Radio (m) | W7: Area (m2)
D8: Tamaño del predio (ha): | F8: Tamaño de la UMF (ha): | H8: No. de individuos/ha (seleccione si o no, según corresponda) | J8: Menor a 100 Individuos /ha | L8: 100 o Más Individuos /ha | N8: % muestreo con respecto a la UMF (depende del número de individuos y del área de la UMF) | R8: Intensidad del inventario (ha) Este valor se calcula automáticamente | V8: Número de indivuos en el área de muestreo
D9: Diseño de muestreo (seleccione si o no en el métodolo que aplique): | G9: Aleatorio | I9: Estratificado | K9: Sistemático | M9: Responsable del inventario: | S9: Fecha del censo, inventario o muestreo: | V9: Cantidad del PFNM en la parcela de muestreo (kg)
D11: Información de los individuos objeto de manejo sostenible | M11: Información de la copa del individuo objeto de manejo sostenible | P11: Estimación de la productividad del individuo | S11: Peso promedio de una unidad de PFNM a aprovechar (g) | T11: Cantidad total (Kg) | U11: Estado fisico del individuo evaluado | V11: Estado sanitario del individuo evaluado | W11: El individuo forestal puede ser objeto de aprovechamiento sostenible Si/No | X11: Observaciones sobre el individuo
B12: ID | C12: Orden | D12: ID-reg | E12: Nombre común | F12: Nombre científico | G12: Parte o Producto a aprovechar | H12: Circunferencia a la Altura del Pecho (CAP) del individuo (cm) | I12: Diamentro a la Altura del Pecho - DAP (m) | J12: Altura Total del individuo forestal (m) | K12: Altura del fuste (m) | L12: Altura de la copa (m) | M12: Diámetro de la copa (en m) - Lado más ancho (Eje X) | N12: Diámetro de la copa (en m) - Lado más angosto (Eje Y) | O12: Volumen de la copa (m3) | P12: Fracción de la copa analizada | Q12: Cantidad del PFNM en la fracción de copa analizada | R12: Cantidad del PFNM en totalidad de la copa
F13: =VLOOKUP(D13,[1]Cod_spp!A:G,2,0) -> #N/A | G13: Semilla | U13: Bueno | V13: Sano | W13: Si | X13: Ninguna
F14: =VLOOKUP(D14,[1]Cod_spp!A:G,2,0) -> #N/A | G14: Semilla | U14: Bueno | V14: Sano | W14: Si | X14: Ninguna
F15: =VLOOKUP(D15,[1]Cod_spp!A:G,2,0) -> #N/A | G15: Semilla | U15: Bueno | V15: Sano | W15: Si | X15: Ninguna
F16: =VLOOKUP(D16,[1]Cod_spp!A:G,2,0) -> #N/A | G16: Semilla | U16: Bueno | V16: Sano | W16: Si | X16: Ninguna
F17: =VLOOKUP(D17,[1]Cod_spp!A:G,2,0) -> #N/A | G17: Semilla | U17: Bueno | V17: Sano | W17: Si | X17: Ninguna
F18: =VLOOKUP(D18,[1]Cod_spp!A:G,2,0) -> #N/A | G18: Semilla | U18: Bueno | V18: Sano | W18: Si | X18: Ninguna
F19: =VLOOKUP(D19,[1]Cod_spp!A:G,2,0) -> #N/A | G19: Semilla | U19: Bueno | V19: Sano | W19: Si | X19: Ninguna
F20: =VLOOKUP(D20,[1]Cod_spp!A:G,2,0) -> #N/A | G20: Semilla | U20: Bueno | V20: Sano | W20: Si | X20: Ninguna
F21: =VLOOKUP(D21,[1]Cod_spp!A:G,2,0) -> #N/A | G21: Semilla | U21: Bueno | V21: Sano | W21: Si | X21: Ninguna
F22: =VLOOKUP(D22,[1]Cod_spp!A:G,2,0) -> #N/A | G22: Semilla | U22: Bueno | V22: Sano | W22: Si | X22: Ninguna
F23: =VLOOKUP(D23,[1]Cod_spp!A:G,2,0) -> #N/A | G23: Semilla | U23: Bueno | V23: Sano | W23: Si | X23: Ninguna
F24: =VLOOKUP(D24,[1]Cod_spp!A:G,2,0) -> #N/A | G24: Semilla | U24: Bueno | V24: Sano | W24: Si | X24: Ninguna
F25: =VLOOKUP(D25,[1]Cod_spp!A:G,2,0) -> #N/A | G25: Semilla | U25: Bueno | V25: Sano | W25: Si | X25: Ninguna
F26: =VLOOKUP(D26,[1]Cod_spp!A:G,2,0) -> #N/A | I26: =(H26/(100*3.1416)) -> 0 | L26: =(J26-K26) -> 0 | O26: =4/3*3.1416*((M26+N26)/2)^3*(1/8*L26) -> 0 | R26: =(Q26/P26) -> #DIV/0! | T26: =(R26*S26/1000) -> #DIV/0!
F27: =VLOOKUP(D27,[1]Cod_spp!A:G,2,0) -> #N/A | I27: =(H27/(100*3.1416)) -> 0 | L27: =(J27-K27) -> 0 | O27: =4/3*3.1416*((M27+N27)/2)^3*(1/8*L27) -> 0 | R27: =(Q27/P27) -> #DIV/0! | T27: =(R27*S27/1000) -> #DIV/0!
F28: =VLOOKUP(D28,[1]Cod_spp!A:G,2,0) -> #N/A | I28: =(H28/(100*3.1416)) -> 0 | L28: =(J28-K28) -> 0 | O28: =4/3*3.1416*((M28+N28)/2)^3*(1/8*L28) -> 0 | R28: =(Q28/P28) -> #DIV/0! | T28: =(R28*S28/1000) -> #DIV/0!
F29: =VLOOKUP(D29,[1]Cod_spp!A:G,2,0) -> #N/A | I29: =(H29/(100*3.1416)) -> 0 | L29: =(J29-K29) -> 0 | O29: =4/3*3.1416*((M29+N29)/2)^3*(1/8*L29) -> 0 | R29: =(Q29/P29) -> #DIV/0! | T29: =(R29*S29/1000) -> #DIV/0!
F30: =VLOOKUP(D30,[1]Cod_spp!A:G,2,0) -> #N/A | I30: =(H30/(100*3.1416)) -> 0 | L30: =(J30-K30) -> 0 | O30: =4/3*3.1416*((M30+N30)/2)^3*(1/8*L30) -> 0 | R30: =(Q30/P30) -> #DIV/0! | T30: =(R30*S30/1000) -> #DIV/0!
F31: =VLOOKUP(D31,[1]Cod_spp!A:G,2,0) -> #N/A | I31: =(H31/(100*3.1416)) -> 0 | L31: =(J31-K31) -> 0 | O31: =4/3*3.1416*((M31+N31)/2)^3*(1/8*L31) -> 0 | R31: =(Q31/P31) -> #DIV/0! | T31: =(R31*S31/1000) -> #DIV/0!
F32: =VLOOKUP(D32,[1]Cod_spp!A:G,2,0) -> #N/A | I32: =(H32/(100*3.1416)) -> 0 | L32: =(J32-K32) -> 0 | O32: =4/3*3.1416*((M32+N32)/2)^3*(1/8*L32) -> 0 | R32: =(Q32/P32) -> #DIV/0! | T32: =(R32*S32/1000) -> #DIV/0!
F33: =VLOOKUP(D33,[1]Cod_spp!A:G,2,0) -> #N/A | I33: =(H33/(100*3.1416)) -> 0 | L33: =(J33-K33) -> 0 | O33: =4/3*3.1416*((M33+N33)/2)^3*(1/8*L33) -> 0 | R33: =(Q33/P33) -> #DIV/0! | T33: =(R33*S33/1000) -> #DIV/0!
F34: =VLOOKUP(D34,[1]Cod_spp!A:G,2,0) -> #N/A | I34: =(H34/(100*3.1416)) -> 0 | L34: =(J34-K34) -> 0 | O34: =4/3*3.1416*((M34+N34)/2)^3*(1/8*L34) -> 0 | R34: =(Q34/P34) -> #DIV/0! | T34: =(R34*S34/1000) -> #DIV/0!
F35: =VLOOKUP(D35,[1]Cod_spp!A:G,2,0) -> #N/A | I35: =(H35/(100*3.1416)) -> 0 | L35: =(J35-K35) -> 0 | O35: =4/3*3.1416*((M35+N35)/2)^3*(1/8*L35) -> 0 | R35: =(Q35/P35) -> #DIV/0! | T35: =(R35*S35/1000) -> #DIV/0!
F36: =VLOOKUP(D36,[1]Cod_spp!A:G,2,0) -> #N/A | I36: =(H36/(100*3.1416)) -> 0 | L36: =(J36-K36) -> 0 | O36: =4/3*3.1416*((M36+N36)/2)^3*(1/8*L36) -> 0 | R36: =(Q36/P36) -> #DIV/0! | T36: =(R36*S36/1000) -> #DIV/0!
F37: =VLOOKUP(D37,[1]Cod_spp!A:G,2,0) -> #N/A | I37: =(H37/(100*3.1416)) -> 0 | L37: =(J37-K37) -> 0 | O37: =4/3*3.1416*((M37+N37)/2)^3*(1/8*L37) -> 0 | R37: =(Q37/P37) -> #DIV/0! | T37: =(R37*S37/1000) -> #DIV/0!
... F42: =VLOOKUP(D42,[1]Cod_spp!A:G,2,0) -> #N/A | I42: =(H42/(100*3.1416)) -> 0 | L42: =(J42-K42) -> 0 | O42: =4/3*3.1416*((M42+N42)/2)^3*(1/8*L42) -> 0 | R42: =(Q42/P42) -> #DIV/0! | T42: =(R42*S42/1000) -> #DIV/0!

Sheet Determinación_Vol_MS
C2: Formato para presentación de Informe de Censo o Inventario para Manejo Sostenible de Especies con Protocolo
C3: Corporación para el Desarrollo Sostenible del sur de la Amazonia
C4: Plantilla para Determinación de Volumenes a Aprovechar de las Especies Objeto de Manejo Sostenible
C5: Código: F-LAR-072 | F5: Versión: 2.0 | I5: Fecha: 08/05/2025
B7: DETERMINACION DEL VOLUMEN DE LA FLORA SILVESTRE Y DE LOS PRODUCTOS FORESTALES NO MADERABLES A COSECHAR
B8: En este formulario se debe hacer un resumen general por cada una de las especies de interés de manejo sostenible, que se relacionan o presentan la información en los formularios anteriores. Con esta información resumen de su solicitud se debe diligenciar las casillas de la sección 5.1 de la plataforma VITAL que se llama Información de las especies objeto de la solicitud de aprovechamiento forestal o manejo sostenible de flora silvestre y los productos forestales no maderables y método, en el módulo APROVECHAMIENTO O MANEJO SOSTENIBLE: Especies objeto de la solicitud: Agregar.
B10: ID_reg | C10: Nombre común | D10: Nombre cientifíco | E10: Veda Nacional o regional | F10: Categoria de amenaza | G10: Habito | H10: Número o cantidad total de individuos de cada especie, existentes en la UMF | I10: Parte o PFNM del individuo objeto de manejo sostenible, a aprovechar: | J10: Cantidad total del recurso o PFNM en la UMF para cada especie | K10: Cantidad del PFNM a aprovechar por especie | L10: Unidad de medida del PFNM o la parte a aprovechar | M10: % de aprovechamiento solicitado | N10: Precio Unitario del PFNM en el mercado por cada Unidad de Medida indicada. ($$$) | O10: Ingresos esperados por la comercialización del PFNM a aprovechar ($$$) | P10: Usos que se le dará a los PFNM a aprovechar
E11: No | G11: Árbol | I11: Semillas | L11: Kilogramos (Kg) | M11: 65 | O11: =K11*N11 -> 0 | P11: Producción de material vegetal
E12: No | G12: Árbol | I12: Semillas | L12: Kilogramos (Kg) | M12: 66 | O12: =K12*N12 -> 0 | P12: Producción de material vegetal
E13: No | G13: Árbol | I13: Semillas | L13: Kilogramos (Kg) | M13: 68 | O13: =K13*N13 -> 0 | P13: Producción de material vegetal
E14: No | G14: Árbol | I14: Semillas | L14: Kilogramos (Kg) | M14: 53 | O14: =K14*N14 -> 0 | P14: Producción de material vegetal
E15: No | G15: Árbol | I15: Semillas | L15: Kilogramos (Kg) | M15: 79 | O15: =K15*N15 -> 0 | P15: Producción de material vegetal
E16: No | G16: Árbol | I16: Semillas | L16: Kilogramos (Kg) | M16: 70 | O16: =K16*N16 -> 0 | P16: Producción de material vegetal
E17: No | G17: Árbol | I17: Semillas | L17: Kilogramos (Kg) | M17: 77 | O17: =K17*N17 -> 0 | P17: Producción de material vegetal
E18: No | G18: Árbol | I18: Semillas | L18: Kilogramos (Kg) | M18: 60 | O18: =K18*N18 -> 0 | P18: Producción de material vegetal
D19: =VLOOKUP(B19,Cod_spp!A:G,2,0) -> #N/A | M19: =#REF!/#REF!*100 -> #REF! | O19: =K19*N19 -> 0
D20: =VLOOKUP(B20,Cod_spp!A:G,2,0) -> #N/A | M20: =#REF!/#REF!*100 -> #REF! | O20: =K20*N20 -> 0
D21: =VLOOKUP(B21,Cod_spp!A:G,2,0) -> #N/A | M21: =#REF!/#REF!*100 -> #REF! | O21: =K21*N21 -> 0
D22: =VLOOKUP(B22,Cod_spp!A:G,2,0) -> #N/A | M22: =#REF!/#REF!*100 -> #REF! | O22: =K22*N22 -> 0
D23: =VLOOKUP(B23,Cod_spp!A:G,2,0) -> #N/A | M23: =#REF!/#REF!*100 -> #REF! | O23: =K23*N23 -> 0
D24: =VLOOKUP(B24,Cod_spp!A:G,2,0) -> #N/A | M24: =#REF!/#REF!*100 -> #REF! | O24: =K24*N24 -> 0
D25: =VLOOKUP(B25,Cod_spp!A:G,2,0) -> #N/A | M25: =#REF!/#REF!*100 -> #REF! | O25: =K25*N25 -> 0
D26: =VLOOKUP(B26,Cod_spp!A:G,2,0) -> #N/A | M26: =#REF!/#REF!*100 -> #REF! | O26: =K26*N26 -> 0
D27: =VLOOKUP(B27,Cod_spp!A:G,2,0) -> #N/A | M27: =#REF!/#REF!*100 -> #REF! | O27: =K27*N27 -> 0
D28: =VLOOKUP(B28,Cod_spp!A:G,2,0) -> #N/A | M28: =#REF!/#REF!*100 -> #REF! | O28: =K28*N28 -> 0
D29: =VLOOKUP(B29,Cod_spp!A:G,2,0) -> #N/A | M29: =#REF!/#REF!*100 -> #REF! | O29: =K29*N29 -> 0
D30: =VLOOKUP(B30,Cod_spp!A:G,2,0) -> #N/A | M30: =#REF!/#REF!*100 -> #REF! | O30: =K30*N30 -> 0
... D34: =VLOOKUP(B34,Cod_spp!A:G,2,0) -> #N/A | M34: =#REF!/#REF!*100 -> #REF! | O34: =K34*N34 -> 0
D35: =VLOOKUP(B35,Cod_spp!A:G,2,0) -> #N/A | M35: =#REF!/#REF!*100 -> #REF! | O35: =J35*N13 -> 0
D36: =VLOOKUP(B36,Cod_spp!A:G,2,0) -> #N/A | M36: =#REF!/#REF!*100 -> #REF! | O36: =J36*N14 -> 0
D37: =VLOOKUP(B37,Cod_spp!A:G,2,0) -> #N/A | M37: =#REF!/#REF!*100 -> #REF! | O37: =J37*N15 -> 0
D38: =VLOOKUP(B38,Cod_spp!A:G,2,0) -> #N/A | M38: =#REF!/#REF!*100 -> #REF! | O38: =J38*N16 -> 0
D39: =VLOOKUP(B39,Cod_spp!A:G,2,0) -> #N/A | M39: =#REF!/#REF!*100 -> #REF! | O39: =J39*N17 -> 0
D40: =VLOOKUP(B40,Cod_spp!A:G,2,0) -> #N/A | M40: =#REF!/#REF!*100 -> #REF! | O40: =J40*N18 -> 0

Sheet Rutas_Movilización
C1: Formato para presentación de Informe de Censo o Inventario para Manejo Sostenible de Especies con Protocolo
C2: Corporación para el Desarrollo Sostenible del sur de la Amazonia
C3: Plantilla para el Registro de Rutas de movilización de Productos Forestales No Maderables cosechados
C4: Código: F-LAR-072 | E4: Versión: 2.0 | H4: Fecha: 08/05/2025
B6: Tipo de transporte | C6: Origen de los PFNM | G6: Destino de los PFNM
C7: Punto de Referencia | D7: Vereda/Corregimiento | E7: Municipio | F7: Departamento | G7: Punto de Referencia | H7: Vereda/Corregimiento | I7: Municipio | J7: Departamento
B8: Terretre | E8: Solano | F8: Caquetá | J8: Caquetá
B9: Terretre | E9: Solano | F9: Caquetá | J9: Caquetá
B10: Terretre | E10: Solano | F10: Caquetá | J10: Caquetá
B11: Terretre | E11: Solano | F11: Caquetá | J11: Caquetá
B12: Terretre | E12: Solano | F12: Caquetá | J12: Caquetá
B13: Terretre | E13: Solano | F13: Caquetá | J13: Caquetá
B14: Terretre | E14: Solano | F14: Caquetá | J14: Caquetá
B15: Terretre | E15: Solano | F15: Caquetá | J15: Caquetá
B16: Terretre | E16: Solano | F16: Caquetá | J16: Caquetá
B17: Terretre | E17: Solano | F17: Caquetá | J17: Caquetá
B18: Terretre | E18: Solano | F18: Caquetá | J18: Caquetá
B19: Terretre | E19: Solano | F19: Caquetá | J19: Caquetá
... B23: Terretre | E23: Solano | F23: Caquetá | J23: Caquetá

Sheet F-LAR-025_Costos_Inversión 
B1: Corporación para el Desarrollo Sostenible del Sur de la Amazonia | E1: Corpoamazonia emitirá la respectiva liquidación por concepto de evaluación del trámite
B2: FORMATO DE AUTODECLARACIÓN DE COSTOS DE INVERSIÓN Y OPERACIÓN DEL PROYECTO
E3: Versión 1.0 | F3: Página 1 de 2
F4: F-LAR-025
A6: PARTE 1 - COSTOS DE INVERSION
A7: DESCRIPCION | C7: UNIDAD DE MEDIDA | D7: CANTIDAD | E7: VALOR UNITARIO ($) | F7: VALOR TOTAL ($)
A8: 1. Estudios técnicos, jurídicos, económicos y Ambientales: Estudios que se hayan realizado o se requieran realizar para el desarrollo del proyecto, obra o actividad, en etapa de construccion o implementación.
A9: Profesional | C9: Dia | D9: 5 | E9: 100000 | F9: =D9*E9 -> 500000
F10: =D10*E10 -> 0
F11: =D11*E11 -> 0
F12: =D12*E12 -> 0
F13: =D13*E13 -> 0
F14: =D14*E14 -> 0
F15: =D15*E15 -> 0
F16: =D16*E16 -> 0
F17: =D17*E17 -> 0
F18: =D18*E18 -> 0
A19: SUBTOTAL | F19: =SUM(F9:F18) -> 500000
A20: 2. Predios o terrenos: Valor del (los) predio (s) o terreno (s) donde se va a ejecutar el proyecto, obra o actividad, para el desarrollo o o implementación del proyecto (PROPIO O ALQUILADO), incluya servidumbres.
C21: ha | E21: 5000000 | F21: =D21*E21 -> 0
F22: =D22*E22 -> 0
F23: =D23*E23 -> 0
F24: =D24*E24 -> 0
F25: =D25*E25 -> 0
A26: SUBTOTAL | F26: =SUM(F21:F25) -> 0
A27: 3.Obras civiles: Costos de diseño y costos directos e indirectos de las obras a ejecutar (principales y accesorios), necesarias para el desarrollo del proyecto, obra o actividad, en etapa de construccion.
A28: N/A | C28: N/A | F28: =D28*E28 -> 0
F29: =D29*E29 -> 0
F30: =D30*E30 -> 0
F31: =D31*E31 -> 0
F32: =D32*E32 -> 0
F33: =D33*E33 -> 0
F34: =D34*E34 -> 0
F35: =D35*E35 -> 0
F36: =D36*E36 -> 0
F37: =D37*E37 -> 0
A38: SUBTOTAL | F38: =SUM(F28:F37) -> 0
A39: 4. Mano de obra: Relacione la mano de obra (calificada y no calificada) necesaria para el desarrollo del proyecto, obra o actividad, en etapa de construccion o implementación.
A40: Baquiano | C40: Dia | D40: 5 | E40: 60000 | F40: =D40*E40 -> 300000
F41: =D41*E41 -> 0
F42: =D42*E42 -> 0
F43: =D43*E43 -> 0
F44: =D44*E44 -> 0
F45: =D45*E45 -> 0
F46: =D46*E46 -> 0
F47: =D47*E47 -> 0
F48: =D48*E48 -> 0
F49: =D49*E49 -> 0
F50: =D50*E50 -> 0
F51: =D51*E51 -> 0
A52: SUBTOTAL | F52: =SUM(F40:F51) -> 300000
A53: 5. Maquinaria y equipos: Costos de adquisición de maquinaria y equipos necesarios para el desarrollo del proyecto, obra o actividad, en etapa de construccion o implementación.
A54: Pintura Asfáltica | C54: UND | D54: 1 | E54: 37000 | F54: =D54*E54 -> 37000
A55: Thiner | C55: UND | D55: 1 | E55: 18000 | F55: =D55*E55 -> 18000
A56: Brocha | C56: UND | D56: 2 | E56: 9000 | F56: =D56*E56 -> 18000
A57: Puntillas de Acero | C57: CAJA | D57: 1 | E57: 5000 | F57: =D57*E57 -> 5000
A58: Placa | C58: UND | D58: 13 | E58: 2000 | F58: =D58*E58 -> 26000
A59: Cascos de Seguridad | C59: UND | D59: 2 | E59: 40000 | F59: =D59*E59 -> 80000
A60: Binoculares | C60: UND | D60: 1 | E60: 250000 | F60: =D60*E60 -> 250000
A61: Decametro X 30 m | C61: UND | D61: 1 | E61: 25000 | F61: =D61*E61 -> 25000
F62: =D62*E62 -> 0
F63: =D63*E63 -> 0
F64: =D64*E64 -> 0
F65: =D65*E65 -> 0
A66: SUBTOTAL | F66: =SUM(F54:F65) -> 459000
A67: 6. Otros bienes e inversiones
F68: =D68*E68 -> 0
F69: =D69*E69 -> 0
F70: =D70*E70 -> 0
F71: =D71*E71 -> 0
F72: =D72*E72 -> 0
A73: SUBTOTAL | F73: =SUM(F68:F72) -> 0
A75: TOTAL COSTOS DE INVERSION (1) | E75: =F19+F26+F38+F52+F66+F73 -> 1259000
A76: IMPRIMIR PARTE 2 AL RESPALDO

Sheet F-LAR-025_Costos_Operación
B1: Corporación para el Desarrollo Sostenible del Sur de la Amazonia | E1: Corpoamazonia emitirá la respectiva liquidación por concepto de evaluación del trámite
B2: FORMATO DE AUTODECLARACIÓN DE COSTOS DE INVERSIÓN Y OPERACIÓN DEL PROYECTO
E3: Versión 1.0 | F3: Página 2 de 2
F4: F-LAR-025
A6: PARTE 2 - COSTOS DE OPERACIÓN
A7: DESCRIPCION | C7: UNIDAD DE MEDIDA | D7: CANTIDAD | E7: VALOR UNITARIO ($) | F7: VALOR TOTAL ($)
A8: 1. MATERIAS PRIMAS E INSUMOS: Valor las materias primas a emplear durante la ejecución del proyecto, obra o actividad.
A9: Desgarretadora | C9: UND | D9: 1 | E9: 250000 | F9: =E9*D9 -> 250000
A10: Bolsas Hermeticas | C10: UND | D10: 20 | E10: 10000 | F10: =E10*D10 -> 200000
A11: Nevera de icopor | C11: UND | D11: 2 | E11: 40000 | F11: =E11*D11 -> 80000
A12: Tijeras Podadoras | C12: UND | D12: 1 | E12: 20000 | F12: =E12*D12 -> 20000
A13: Polisombra | C13: Rollo x11 m | D13: 1 | E13: 91000 | F13: =E13*D13 -> 91000
A14: Rollo de cabuya | C14: UND X 750 m | D14: 1 | E14: 18000 | F14: =E14*D14 -> 18000
A15: Rollo de cinta de enmascarar | C15: UND | D15: 1 | E15: 4200 | F15: =E15*D15 -> 4200
A16: Marcador Sharpie de punta fina | C16: UND | D16: 1 | E16: 5000 | F16: =E16*D16 -> 5000
F19: =E19*D19 -> 0
F20: =E20*D20 -> 0
A21: SUBTOTAL | F21: =SUM(F9:F20) -> 668200
A22: 2. MANO DE OBRA
A23: Mano de obra calificada | C23: Dias/año | D23: 24 | E23: 110000 | F23: =E23*D23 -> 2640000
A24: Mano de obra no calificada | C24: Dias/año | D24: 36 | E24: 60000 | F24: =E24*D24 -> 2160000
F25: =E25*D25 -> 0
F26: =E26*D26 -> 0
F27: =E27*D27 -> 0
F28: =E28*D28 -> 0
F29: =E29*D29 -> 0
F30: =E30*D30 -> 0
F31: =E31*D31 -> 0
F32: =E32*D32 -> 0
F33: =E33*D33 -> 0
F34: =E34*D34 -> 0
F35: =E35*D35 -> 0
F36: =E36*D36 -> 0
A37: SUBTOTAL | F37: =SUM(F23:F36) -> 4800000
A38: 3. ARRENDAMIENTOS, ALQUILERES, SERVICIOS PÚBLICOS, SEGUROS Y OTROS GASTOS GENERADOS.
A39: N/A | C39: N/A | F39: =E39*D39 -> 0
F40: =E40*D40 -> 0
F41: =E41*D41 -> 0
F42: =E42*D42 -> 0
F43: =E43*D43 -> 0
F44: =E44*D44 -> 0
F45: =E45*D45 -> 0
F46: =E46*D46 -> 0
F47: =E47*D47 -> 0
F48: =E48*D48 -> 0
A49: SUBTOTAL | F49: =SUM(F39:F48) -> 0
A50: 4. MANTENIMIENTO, REPARACIÓN Y/O REPOSICIÓN DE EQUIPOS, INSTRUMENTOS Y/O ELEMENTOS REQUERIDOS.
A51: N/A | C51: N/A | F51: =E51*D51 -> 0
F52: =E52*D52 -> 0
F53: =E53*D53 -> 0
F54: =E54*D54 -> 0
F55: =E55*D55 -> 0
F56: =E56*D56 -> 0
F57: =E57*D57 -> 0
F58: =E58*D58 -> 0
A59: SUBTOTAL | F59: =SUM(F51:F58) -> 0
A60: 5. DESMANTELAMIENTO (Pago de demoliciones, adecuación, transporte)
A61: N/A | C61: N/A | F61: =E61*D61 -> 0
F62: =E62*D62 -> 0
F63: =E63*D63 -> 0
F64: =E64*D64 -> 0
F65: =E65*D65 -> 0
A66: SUBTOTAL | F66: =SUM(F61:F65) -> 0
A68: TOTAL COSTOS OPERACIÓN (2) | E68: =F21+F37+F49+F59+F66 -> 5468200
A70: TOTAL COSTO DEL PROYECTO (1. INVERSIÓN + 2. OPERACION) | E70: ='F-LAR-025_Costos_Inversión '!E75+'F-LAR-025_Costos_Operación'!E68 -> 6727200
C72: DATOS DE USUARIO: | E72: REVISÓ: CORPOAMAZONIA
A73: NOMBRE
A74: IDENTIFICACIÓN
A75: DIRECCIÓN
A76: TELEFONO
A77: FIRMA
A78: FECHA
A79: CARGO - ROL | C79: Propietario

Sheet Cod_spp
A1: ID_reg | B1: NombreCientífico | C1: Familia APG | D1: Género | E1: Especie | F1: Clasificador | G1: Nom._Comunes | H1: Cat_Amenaza_Res_0126/2024 | I1: Veda_Nro._Act_Adtivo | J1: Cat._Dec._1390/2018 | K1: Apen._CITES | L1: Familia _SINCHI | M1: ID_Fam | N1: ID_Gen | O1: ID_sp
A2: 100100100 | B2: Muerto | C2: _SD | D2: _Muerto | E2: Muerto | F2: _SD | G2: Muerto | H2: - | I2: - | J2: - | K2: - | L2: _SD | M2: 100 | N2: 100 | O2: 100
A3: 101100100 | B3: Sin Determinar | C3: _Sin Determinar | D3: _Sin Determinar | E3: _Sin Determinar | F3: _Sin Determinar | G3: _Sin Determinar | H3: - | I3: - | J3: - | K3: - | L3: _Sin Determinar | M3: 101 | N3: 100 | O3: 100
A4: 102100100 | B4: Aphelandra sp. | C4: Acanthaceae | D4: Aphelandra | E4: sp. | F4: - | G4: Coralillo silvestre | Vara verde | H4: - | I4: - | J4: Otras | K4: - | L4: Acanthaceae | M4: 102 | N4: 100 | O4: 100
A5: 102100101 | B5: Aphelandra aurantiaca (Scheidw.) Lindl. | C5: Acanthaceae | D5: Aphelandra | E5: aurantiaca | F5: (Scheidw.) Lindl. | G5: - | H5: - | I5: - | J5: Otras | K5: - | L5: Acanthaceae | M5: 102 | N5: 100 | O5: 101
A6: 102100102 | B6: Aphelandra crenata Leonard | C6: Acanthaceae | D6: Aphelandra | E6: crenata | F6: Leonard | G6: - | H6: - | I6: - | J6: Otras | K6: - | L6: Acanthaceae | M6: 102 | N6: 100 | O6: 102
A7: 102100103 | B7: Aphelandra crispata Leonard | C7: Acanthaceae | D7: Aphelandra | E7: crispata | F7: Leonard | G7: Col de monte silvestre | Ginyer silvestre | H7: - | I7: - | J7: Otras | K7: - | L7: Acanthaceae | M7: 102 | N7: 100 | O7: 103
A8: 102100104 | B8: Aphelandra hylaea Leonard | C8: Acanthaceae | D8: Aphelandra | E8: hylaea | F8: Leonard | G8: - | H8: - | I8: - | J8: Otras | K8: - | L8: Acanthaceae | M8: 102 | N8: 100 | O8: 104
A9: 102100105 | B9: Aphelandra impressa Lindau | C9: Acanthaceae | D9: Aphelandra | E9: impressa | F9: Lindau | G9: - | H9: - | I9: - | J9: Otras | K9: - | L9: Acanthaceae | M9: 102 | N9: 100 | O9: 105
A10: 102100106 | B10: Aphelandra kingii Wassh. | C10: Acanthaceae | D10: Aphelandra | E10: kingii | F10: Wassh. | G10: - | H10: - | I10: - | J10: Otras | K10: - | L10: Acanthaceae | M10: 102 | N10: 100 | O10: 106
A11: 102100107 | B11: Aphelandra macrostachya Nees | C11: Acanthaceae | D11: Aphelandra | E11: macrostachya | F11: Nees | G11: - | H11: - | I11: - | J11: Otras | K11: - | L11: Acanthaceae | M11: 102 | N11: 100 | O11: 107
A12: 102100108 | B12: Aphelandra maculata (Tafalla ex Nees) Voss | C12: Acanthaceae | D12: Aphelandra | E12: maculata | F12: (Tafalla ex Nees) Voss | G12: - | H12: - | I12: - | J12: Otras | K12: - | L12: Acanthaceae | M12: 102 | N12: 100 | O12: 108
A13: 102100109 | B13: Aphelandra martiusii Wassh. | C13: Acanthaceae | D13: Aphelandra | E13: martiusii | F13: Wassh. | G13: - | H13: - | I13: - | J13: Otras | K13: - | L13: Acanthaceae | M13: 102 | N13: 100 | O13: 109
... A296: 112101128 | B296: Annona nitida Mart. | C296: Annonaceae | D296: Annona | E296: nitida | F296: Mart. | G296: Guanábana | H296: - | I296: - | J296: Otras | K296: - | L296: Annonaceae | M296: 112 | N296: 101 | O296: 128
A297: 112101129 | B297: Annona papilionella (Diels) H. Rainer | C297: Annonaceae | D297: Annona | E297: papilionella | L297: Annonaceae | M297: 112 | N297: 101 | O297: 129
A298: 112101130 | B298: Annona pulchra H.Rainer | C298: Annonaceae | D298: Annona | E298: pulchra | F298: H.Rainer | G298: - | H298: - | I298: - | J298: Otras | K298: - | L298: Annonaceae | M298: 112 | N298: 101 | O298: 130
A299: 112101131 | B299: Annona rensoniana (Standl.) H.Rainer | C299: Annonaceae | D299: Annona | E299: rensoniana | F299: (Standl.) H.Rainer | G299: - | H299: - | I299: - | J299: Otras | K299: - | L299: Annonaceae | M299: 112 | N299: 101 | O299: 131
A300: 112101132 | B300: Annona rigida R.E.Fr. | C300: Annonaceae | D300: Annona | E300: rigida | F300: R.E.Fr. | G300: - | H300: - | I300: - | J300: Otras | K300: - | L300: Annonaceae | M300: 112 | N300: 101 | O300: 132
A301: 112101133 | B301: Annona scandens Diels | C301: Annonaceae | D301: Annona | E301: scandens | F301: Diels | G301: - | H301: - | I301: - | J301: Otras | K301: - | L301: Annonaceae | M301: 112 | N301: 101 | O301: 133
A302: 112101134 | B302: Annona sericea Dunal | C302: Annonaceae | D302: Annona | E302: sericea | F302: Dunal | G302: - | H302: - | I302: - | J302: Otras | K302: - | L302: Annonaceae | M302: 112 | N302: 101 | O302: 134
A303: 112102100 | B303: Bocageopsis sp. | C303: Annonaceae | D303: Bocageopsis | E303: sp. | F303: - | G303: - | H303: - | I303: - | J303: Otras | K303: - | L303: Annonaceae | M303: 112 | N303: 102 | O303: 100
A304: 112102101 | B304: Bocageopsis canescens (Benth.) R.E.Fr. | C304: Annonaceae | D304: Bocageopsis | E304: canescens | F304: (Benth.) R.E.Fr. | G304: Carguero de sabana | Carguero no propio | Espintana blanco | carguero negro | Carguero | H304: - | I304: - | J304: Otras | K304: - | L304: Annonaceae | M304: 112 | N304: 102 | O304: 101
A305: 112102102 | B305: Bocageopsis mattogrossensis (R.E.Fr.) R.E.Fr. | C305: Annonaceae | D305: Bocageopsis | E305: mattogrossensis | F305: (R.E.Fr.) R.E.Fr. | G305: - | H305: - | I305: - | J305: Otras | K305: - | L305: Annonaceae | M305: 112 | N305: 102 | O305: 102
A306: 112102103 | B306: Bocageopsis multiflora (Mart.) R.E.Fr. | C306: Annonaceae | D306: Bocageopsis | E306: multiflora | F306: (Mart.) R.E.Fr. | G306: Chucho | Carguero de sabana | H306: - | I306: - | J306: Otras | K306: - | L306: Annonaceae | M306: 112 | N306: 102 | O306: 103
A307: 112103100 | B307: Cananga odorata (Lam.) Hook.f. & Thomson | C307: Annonaceae | D307: Cananga | E307: odorata | F307: (Lam.) Hook.f. & Thomson | G307: Ilán Ilán | Flor de amor | H307: - | I307: - | J307: Especial | K307: - | L307: Annonaceae | M307: 112 | N307: 103 | O307: 100
A308: 112104100 | B308: Cremastosperma sp. | C308: Annonaceae | D308: Cremastosperma | E308: sp. | F308: - | G308: - | H308: - | I308: - | J308: Otras | K308: - | L308: Annonaceae | M308: 112 | N308: 104 | O308: 100
A309: 112104101 | B309: Cremastosperma cauliflorum R.E.Fr. | C309: Annonaceae | D309: Cremastosperma | E309: cauliflorum | F309: R.E.Fr. | G309: Nagüí | H309: - | I309: - | J309: Otras | K309: - | L309: Annonaceae | M309: 112 | N309: 104 | O309: 101
... A2140: 147113107 | B2140: Tontelea passiflora (Vell.) Lombardi | C2140: Celastraceae | D2140: Tontelea | E2140: passiflora | F2140: (Vell.) Lombardi | G2140: Ojo de buey | Chuchuhuaza | H2140: - | I2140: - | J2140: Otras | K2140: - | L2140: Hippocrateaceae | M2140: 147 | N2140: 113 | O2140: 107
A2141: 147114100 | B2141: Zinowiewia integerrima (Turcz.) Turcz. | C2141: Celastraceae | D2141: Zinowiewia | E2141: integerrima | F2141: (Turcz.) Turcz. | G2141: Costillo | J2141: Otras | L2141: NL | M2141: 147 | N2141: 114 | O2141: 100
A2142: 148100100 | B2142: Hedyosmum sp. | C2142: Chloranthaceae | D2142: Hedyosmum | E2142: sp. | F2142: - | G2142: Guayusa | Oyoco | H2142: - | I2142: - | J2142: Otras | K2142: - | L2142: Chloranthaceae | M2142: 148 | N2142: 100 | O2142: 100
A2143: 148100101 | B2143: Hedyosmum bonplandianum Kunth | C2143: Chloranthaceae | D2143: Hedyosmum | E2143: bonplandianum | F2143: Kunth | G2143: Granicillo | Granizo | H2143: - | I2143: - | J2143: Otras | K2143: - | L2143: Chloranthaceae | M2143: 148 | N2143: 100 | O2143: 101
A2144: 148100102 | B2144: Hedyosmum cuatrecazanum Occhioni | C2144: Chloranthaceae | D2144: Hedyosmum | E2144: cuatrecazanum | F2144: Occhioni | G2144: Guayusa | H2144: - | I2144: - | J2144: Otras | K2144: - | L2144: Chloranthaceae | M2144: 148 | N2144: 100 | O2144: 102
A2145: 148100103 | B2145: Hedyosmum goudotianum Solms | C2145: Chloranthaceae | D2145: Hedyosmum | E2145: goudotianum | F2145: Solms | G2145: Guayusa | Salado | H2145: - | I2145: - | J2145: Otras | K2145: - | L2145: Chloranthaceae | M2145: 148 | N2145: 100 | O2145: 103
A2146: 148100104 | B2146: Hedyosmum racemosum (Ruiz & Pav.) G.Don | C2146: Chloranthaceae | D2146: Hedyosmum | E2146: racemosum | F2146: (Ruiz & Pav.) G.Don | G2146: Granizo | Uraco | H2146: - | I2146: - | J2146: Otras | K2146: - | L2146: Chloranthaceae | M2146: 148 | N2146: 100 | O2146: 104
A2147: 148100105 | B2147: Hedyosmum sprucei Solms | C2147: Chloranthaceae | D2147: Hedyosmum | E2147: sprucei | F2147: Solms | G2147: Silvador | H2147: - | I2147: - | J2147: Otras | K2147: - | L2147: Chloranthaceae | M2147: 148 | N2147: 100 | O2147: 105
A2148: 149100100 | B2148: Acioa sp. | C2148: Chrysobalanaceae | D2148: Acioa | E2148: sp. | F2148: - | G2148: - | H2148: - | I2148: - | J2148: Otras | K2148: - | L2148: Chrysobalanaceae | M2148: 149 | N2148: 100 | O2148: 100
A2149: 149100101 | B2149: Acioa dolichopoda (Prance) Sothers & Prance | C2149: Chrysobalanaceae | D2149: Acioa | E2149: dolichopoda | F2149: (Prance) Sothers & Prance | G2149: Aguire | Guayabene | Algarrobo | Almendro | Talega Huayo | Hamaca Huayo | H2149: - | I2149: - | J2149: Otras | K2149: - | L2149: Chrysobalanaceae | M2149: 149 | N2149: 100 | O2149: 101
A2150: 149100102 | B2150: Acioa longipendula (Pilg.) Sothers & Prance | C2150: Chrysobalanaceae | D2150: Acioa | E2150: longipendula | F2150: (Pilg.) Sothers & Prance | G2150: Aguire | H2150: - | I2150: - | J2150: Otras | K2150: - | L2150: Chrysobalanaceae | M2150: 149 | N2150: 100 | O2150: 102
A2151: 149100103 | B2151: Acioa schultesii Maguire | C2151: Chrysobalanaceae | D2151: Acioa | E2151: schultesii | F2151: Maguire | G2151: - | H2151: - | I2151: - | J2151: Otras | K2151: - | L2151: Chrysobalanaceae | M2151: 149 | N2151: 100 | O2151: 103
A2152: 149101100 | B2152: Chrysobalanus icaco L. | C2152: Chrysobalanaceae | D2152: Chrysobalanus | E2152: icaco | F2152: L. | G2152: Icaco | H2152: - | I2152: - | J2152: Otras | K2152: - | L2152: Chrysobalanaceae | M2152: 149 | N2152: 101 | O2152: 100
A2153: 149102100 | B2153: Couepia sp. | C2153: Chrysobalanaceae | D2153: Couepia | E2153: sp. | F2153: - | G2153: Agüire | H2153: - | I2153: - | J2153: Otras | K2153: - | L2153: Chrysobalanaceae | M2153: 149 | N2153: 102 | O2153: 100
... A3545: 185111102 | B3545: Arachis pintoi Krapov. & W.C.Greg. | C3545: Fabaceae | D3545: Arachis | E3545: pintoi | F3545: Krapov. & W.C.Greg. | G3545: - | H3545: - | I3545: - | J3545: Otras | K3545: - | L3545: Fabaceae | M3545: 185 | N3545: 111 | O3545: 102
A3546: 185112100 | B3546: Balizia pedicellaris (DC.) Barneby & J.W. | C3546: Fabaceae | D3546: Balizia | E3546: pedicellaris | F3546: (DC.) Barneby & J.W. | M3546: 185 | N3546: 112 | O3546: 100
A3547: 185113100 | B3547: Barbieria pinnata (Pers.) Baill. | C3547: Fabaceae | D3547: Barbieria | E3547: pinnata | F3547: (Pers.) Baill. | G3547: - | H3547: - | I3547: - | J3547: Otras | K3547: - | L3547: Fabaceae | M3547: 185 | N3547: 113 | O3547: 100
A3548: 185114100 | B3548: Batesia floribunda Benth. | C3548: Fabaceae | D3548: Batesia | E3548: floribunda | F3548: Benth. | G3548: Chocho | H3548: - | I3548: - | J3548: Otras | K3548: - | L3548: Caesalpiniaceae | M3548: 185 | N3548: 114 | O3548: 100
A3549: 185115100 | B3549: Bauhinia sp. | C3549: Fabaceae | D3549: Bauhinia | E3549: sp. | F3549: - | G3549: - | H3549: - | I3549: - | J3549: Otras | K3549: - | L3549: Caesalpiniaceae | M3549: 185 | N3549: 115 | O3549: 100
A3550: 185115101 | B3550: Bauhinia arborea Wunderlin | C3550: Fabaceae | D3550: Bauhinia | E3550: arborea | F3550: Wunderlin | G3550: - | H3550: - | I3550: - | J3550: Otras | K3550: - | L3550: Caesalpiniaceae | M3550: 185 | N3550: 115 | O3550: 101
A3551: 185115102 | B3551: Bauhinia brachycalyx Ducke | C3551: Fabaceae | D3551: Bauhinia | E3551: brachycalyx | F3551: Ducke | G3551: - | H3551: - | I3551: - | J3551: Otras | K3551: - | L3551: Caesalpiniaceae | M3551: 185 | N3551: 115 | O3551: 102
A3552: 185115103 | B3552: Bauhinia longicuspis Benth. | C3552: Fabaceae | D3552: Bauhinia | E3552: longicuspis | F3552: Benth. | G3552: Pezuño | H3552: - | I3552: - | J3552: Otras | K3552: - | L3552: Caesalpiniaceae | M3552: 185 | N3552: 115 | O3552: 103
A3553: 185115104 | B3553: Bauhinia picta (Kunth) DC. | C3553: Fabaceae | D3553: Bauhinia | E3553: picta | F3553: (Kunth) DC. | G3553: - | H3553: - | I3553: - | J3553: Otras | K3553: - | L3553: Caesalpiniaceae | M3553: 185 | N3553: 115 | O3553: 104
A3554: 185115105 | B3554: Bauhinia tarapotensis Benth. | C3554: Fabaceae | D3554: Bauhinia | E3554: tarapotensis | F3554: Benth. | G3554: Casco de vaca | Patevaca | Casco de buey | Pata de vaca | Peinilla | Machetico | H3554: - | I3554: - | J3554: Otras | K3554: - | L3554: Caesalpiniaceae | M3554: 185 | N3554: 115 | O3554: 105
A3555: 185115106 | B3555: Bauhinia ungulata L. | C3555: Fabaceae | D3555: Bauhinia | E3555: ungulata | F3555: L. | G3555: Patavaca | H3555: - | I3555: - | J3555: Otras | K3555: - | L3555: Caesalpiniaceae | M3555: 185 | N3555: 115 | O3555: 106
A3556: 185116100 | B3556: Bowdichia virgilioides Kunth | C3556: Fabaceae | D3556: Bowdichia | E3556: virgilioides | F3556: Kunth | G3556: Alcornoque | Alcornoco | H3556: - | I3556: - | J3556: Otras | K3556: - | L3556: Fabaceae | M3556: 185 | N3556: 116 | O3556: 100
A3557: 185117100 | B3557: Brownea sp. | C3557: Fabaceae | D3557: Brownea | E3557: sp. | F3557: - | G3557: - | H3557: - | I3557: - | J3557: Otras | K3557: - | L3557: Caesalpiniaceae | M3557: 185 | N3557: 117 | O3557: 100
A3558: 185117101 | B3558: Brownea ariza Benth. | C3558: Fabaceae | D3558: Brownea | E3558: ariza | F3558: Benth. | G3558: Clavellino | Flor de rosa | H3558: - | I3558: - | J3558: Otras | K3558: - | L3558: Caesalpiniaceae | M3558: 185 | N3558: 117 | O3558: 101
... A4028: 185189114 | B4028: Ormosia santaremnensis Ducke | C4028: Fabaceae | D4028: Ormosia | E4028: santaremnensis | F4028: Ducke | G4028: - | H4028: - | I4028: - | J4028: Otras | K4028: - | L4028: Fabaceae | M4028: 185 | N4028: 189 | O4028: 114
A4029: 185189115 | B4029: Ormosia schunkei Rudd | C4029: Fabaceae | D4029: Ormosia | E4029: schunkei | F4029: Rudd | G4029: Chocho | J4029: Otras | L4029: Fabaceae | M4029: 185 | N4029: 189 | O4029: 115
A4030: 185189116 | B4030: Ormosia subsimplex Benth. | C4030: Fabaceae | D4030: Ormosia | E4030: subsimplex | F4030: Benth. | G4030: Chocho | H4030: - | I4030: - | J4030: Otras | K4030: - | L4030: Fabaceae | M4030: 185 | N4030: 189 | O4030: 116
A4031: 185189117 | B4031: Ormosia williamsii Rudd | C4031: Fabaceae | D4031: Ormosia | E4031: williamsii | F4031: Rudd | G4031: - | H4031: - | I4031: - | J4031: Otras | K4031: - | L4031: Fabaceae | M4031: 185 | N4031: 189 | O4031: 117
A4032: 185190100 | B4032: Pachyrhizus tuberosus (Lam.) Spreng. | C4032: Fabaceae | D4032: Pachyrhizus | E4032: tuberosus | F4032: (Lam.) Spreng. | G4032: Fríjol de tubérculo | H4032: - | I4032: - | J4032: Otras | K4032: - | L4032: Fabaceae | M4032: 185 | N4032: 190 | O4032: 100
A4033: 185191100 | B4033: Paloue duckei (Huber) Redden | C4033: Fabaceae | D4033: Paloue | E4033: duckei | F4033: (Huber) Redden | G4033: - | H4033: - | I4033: - | J4033: Otras | K4033: - | L4033: Caesalpiniaceae | M4033: 185 | N4033: 191 | O4033: 100
A4034: 185192100 | B4034: Panurea longifolia Benth. | C4034: Fabaceae | D4034: Panurea | E4034: longifolia | F4034: Benth. | G4034: - | H4034: - | I4034: - | J4034: Otras | K4034: - | L4034: Fabaceae | M4034: 185 | N4034: 192 | O4034: 100
A4035: 185193100 | B4035: Paramachaerium sp. | C4035: Fabaceae | D4035: Paramachaerium | E4035: sp. | F4035: - | G4035: - | H4035: - | I4035: - | J4035: Otras | K4035: - | L4035: Fabaceae | M4035: 185 | N4035: 193 | O4035: 100
A4036: 185194100 | B4036: Parkia sp. | C4036: Fabaceae | D4036: Parkia | E4036: sp. | F4036: - | G4036: Guarango | Guarango amarillo | H4036: - | I4036: - | J4036: Otras | K4036: - | L4036: Mimosaceae | M4036: 185 | N4036: 194 | O4036: 100
A4037: 185194101 | B4037: Parkia balslevii H.C.Hopkins | C4037: Fabaceae | D4037: Parkia | E4037: balslevii | F4037: H.C.Hopkins | G4037: Guarango | H4037: - | I4037: - | J4037: Otras | K4037: - | L4037: Mimosaceae | M4037: 185 | N4037: 194 | O4037: 101
A4038: 185194102 | B4038: Parkia barnebyana H.C.Hopkins | C4038: Fabaceae | D4038: Parkia | E4038: barnebyana | F4038: H.C.Hopkins | G4038: - | H4038: - | I4038: - | J4038: Otras | K4038: - | L4038: Mimosaceae | M4038: 185 | N4038: 194 | O4038: 102
A4039: 185194103 | B4039: Parkia decussata Ducke | C4039: Fabaceae | D4039: Parkia | E4039: decussata | F4039: Ducke | G4039: - | H4039: - | I4039: - | J4039: Otras | K4039: - | L4039: Mimosaceae | M4039: 185 | N4039: 194 | O4039: 103
A4040: 185194104 | B4040: Parkia discolor Benth. | C4040: Fabaceae | D4040: Parkia | E4040: discolor | F4040: Benth. | G4040: Dormidero blanco | Guarango | H4040: - | I4040: - | J4040: Otras | K4040: - | L4040: Mimosaceae | M4040: 185 | N4040: 194 | O4040: 104
A4041: 185194105 | B4041: Parkia igneiflora Ducke | C4041: Fabaceae | D4041: Parkia | E4041: igneiflora | F4041: Ducke | G4041: Guamo negro | Guarango | H4041: - | I4041: - | J4041: Otras | K4041: - | L4041: Mimosaceae | M4041: 185 | N4041: 194 | O4041: 105
... A4181: 185220103 | B4181: Tachigali cavipes (Benth.) J.F.Macbr. | C4181: Fabaceae | D4181: Tachigali | E4181: cavipes | F4181: (Benth.) J.F.Macbr. | G4181: - | H4181: - | I4181: - | J4181: Otras | K4181: - | L4181: Caesalpiniaceae | M4181: 185 | N4181: 220 | O4181: 103
A4182: 185220104 | B4182: Tachigali chrysaloides van der Werff | C4182: Fabaceae | D4182: Tachigali | E4182: chrysaloides | F4182: van der Werff | G4182: Guamo diablo | J4182: Otras | L4182: Caesalpiniaceae | M4182: 185 | N4182: 220 | O4182: 104
A4183: 185220105 | B4183: Tachigali chrysophylla (Poepp.) Zarucchi & Herend. | C4183: Fabaceae | D4183: Tachigali | E4183: chrysophylla | F4183: (Poepp.) Zarucchi & Herend. | G4183: Uatero | Guamo diablo | H4183: - | I4183: - | J4183: Otras | K4183: - | L4183: Caesalpiniaceae | M4183: 185 | N4183: 220 | O4183: 105
A4184: 185220106 | B4184: Tachigali dwyeri (R.S.Cowan) Zarucchi & Herend. | C4184: Fabaceae | D4184: Tachigali | E4184: dwyeri | F4184: (R.S.Cowan) Zarucchi & Herend. | G4184: - | H4184: - | I4184: - | J4184: Otras | K4184: - | L4184: Caesalpiniaceae | M4184: 185 | N4184: 220 | O4184: 106
A4185: 185220107 | B4185: Tachigali eriopetala (Ducke) L.F.GomesdaSilva & H.C.Lima | C4185: Fabaceae | D4185: Tachigali | E4185: eriopetala | F4185: (Ducke) L.F.GomesdaSilva & H.C.Lima | G4185: - | H4185: - | I4185: - | J4185: Otras | K4185: - | L4185: Caesalpiniaceae | M4185: 185 | N4185: 220 | O4185: 107
A4186: 185220108 | B4186: Tachigali formicarum Harms | C4186: Fabaceae | D4186: Tachigali | E4186: formicarum | F4186: Harms | G4186: Tangarana | Castillo | H4186: - | I4186: - | J4186: Otras | K4186: - | L4186: Caesalpiniaceae | M4186: 185 | N4186: 220 | O4186: 108
A4187: 185220109 | B4187: Tachigali guianensis (Benth.) Zarucchi & Herend. | C4187: Fabaceae | D4187: Tachigali | E4187: guianensis | F4187: (Benth.) Zarucchi & Herend. | G4187: - | H4187: - | I4187: - | J4187: Otras | K4187: - | L4187: Caesalpiniaceae | M4187: 185 | N4187: 220 | O4187: 109
A4188: 185220110 | B4188: Tachigali hypoleuca (Benth.) Zarucchi & Herend. | C4188: Fabaceae | D4188: Tachigali | E4188: hypoleuca | F4188: (Benth.) Zarucchi & Herend. | G4188: - | H4188: - | I4188: - | J4188: Otras | K4188: - | L4188: Caesalpiniaceae | M4188: 185 | N4188: 220 | O4188: 110
A4189: 185220111 | B4189: Tachigali inconspicua van der Werff | C4189: Fabaceae | D4189: Tachigali | E4189: inconspicua | F4189: van der Werff | G4189: Guamo diablo | J4189: Otras | L4189: Caesalpiniaceae | M4189: 185 | N4189: 220 | O4189: 111
A4190: 185220112 | B4190: Tachigali loretensis van der Werff | C4190: Fabaceae | D4190: Tachigali | E4190: loretensis | F4190: van der Werff | G4190: - | H4190: - | I4190: - | J4190: Otras | K4190: - | L4190: Caesalpiniaceae | M4190: 185 | N4190: 220 | O4190: 112
A4191: 185220113 | B4191: Tachigali melinonii (Harms) Zarucchi & Herend. | C4191: Fabaceae | D4191: Tachigali | E4191: melinonii | F4191: (Harms) Zarucchi & Herend. | G4191: Palo de bostezo | H4191: - | I4191: - | J4191: Otras | K4191: - | L4191: Caesalpiniaceae | M4191: 185 | N4191: 220 | O4191: 113
A4192: 185220114 | B4192: Tachigali micropetala (Ducke) Zarucchi & Pipoly | C4192: Fabaceae | D4192: Tachigali | E4192: micropetala | F4192: (Ducke) Zarucchi & Pipoly | G4192: - | H4192: - | I4192: - | J4192: Otras | K4192: - | L4192: Caesalpiniaceae | M4192: 185 | N4192: 220 | O4192: 114
A4193: 185220115 | B4193: Tachigali odoratissima (Benth.) Zaruchi & Herend. | C4193: Fabaceae | D4193: Tachigali | E4193: odoratissima | F4193: (Benth.) Zaruchi & Herend. | G4193: Uatero | H4193: - | I4193: - | J4193: Otras | K4193: - | L4193: Caesalpiniaceae | M4193: 185 | N4193: 220 | O4193: 115
A4194: 185220116 | B4194: Tachigali paniculata Aubl. | C4194: Fabaceae | D4194: Tachigali | E4194: paniculata | F4194: Aubl. | G4194: Tangarana negro | Guamo de hoja ancha | H4194: - | I4194: - | J4194: Otras | K4194: - | L4194: Caesalpiniaceae | M4194: 185 | N4194: 220 | O4194: 116
A4195: 185220117 | B4195: Tachigali physophora (Huber) Zarucchi & Herend. | C4195: Fabaceae | D4195: Tachigali | E4195: physophora | F4195: (Huber) Zarucchi & Herend. | G4195: - | H4195: - | I4195: - | J4195: Otras | K4195: - | L4195: Caesalpiniaceae | M4195: 185 | N4195: 220 | O4195: 117
A4196: 185220118 | B4196: Tachigali pilosa van der Werff | C4196: Fabaceae | D4196: Tachigali | E4196: pilosa | F4196: van der Werff | G4196: Guamo blanco | Rayo | guamo manteco | H4196: - | I4196: - | J4196: Otras | K4196: - | L4196: Caesalpiniaceae | M4196: 185 | N4196: 220 | O4196: 118
A4197: 185220119 | B4197: Tachigali plumbea Ducke | C4197: Fabaceae | D4197: Tachigali | E4197: plumbea | F4197: Ducke | G4197: - | H4197: - | I4197: - | J4197: Otras | K4197: - | L4197: Caesalpiniaceae | M4197: 185 | N4197: 220 | O4197: 119
A4198: 185220120 | B4198: Tachigali poeppigiana Tul. | C4198: Fabaceae | D4198: Tachigali | E4198: poeppigiana | F4198: Tul. | G4198: - | H4198: - | I4198: - | J4198: Otras | K4198: - | L4198: Caesalpiniaceae | M4198: 185 | N4198: 220 | O4198: 120
A4199: 185220121 | B4199: Tachigali ptychophysca Benth. | C4199: Fabaceae | D4199: Tachigali | E4199: ptychophysca | F4199: Benth. | G4199: - | H4199: - | I4199: - | J4199: Otras | K4199: - | L4199: Caesalpiniaceae | M4199: 185 | N4199: 220 | O4199: 121
A4200: 185220122 | B4200: Tachigali rigida Ducke | C4200: Fabaceae | D4200: Tachigali | E4200: rigida | F4200: Ducke | G4200: - | H4200: - | I4200: - | J4200: Otras | K4200: - | L4200: Caesalpiniaceae | M4200: 185 | N4200: 220 | O4200: 122
A4201: 185220123 | B4201: Tachigali schultesiana Dwyer | C4201: Fabaceae | D4201: Tachigali | E4201: schultesiana | F4201: Dwyer | G4201: - | H4201: - | I4201: - | J4201: Otras | K4201: - | L4201: Caesalpiniaceae | M4201: 185 | N4201: 220 | O4201: 123
... A9326: 290103101 | B9326: Manilkara huberi (Ducke) Standl. | C9326: Sapotaceae | D9326: Manilkara | E9326: huberi | F9326: (Ducke) Standl. | G9326: Níspero | H9326: - | I9326: - | J9326: Especial | K9326: - | L9326: Sapotaceae | M9326: 290 | N9326: 103 | O9326: 101
A9327: 290103102 | B9327: Manilkara sp. - | C9327: Sapotaceae | D9327: Manilkara | E9327: sp. | F9327: - | G9327: - | H9327: - | I9327: - | K9327: - | L9327: Sapotaceae | M9327: 290 | N9327: 103 | O9327: 102
A9328: 290103103 | B9328: Manilkara zapata (L.) P.Royen | C9328: Sapotaceae | D9328: Manilkara | E9328: zapata | F9328: (L.) P.Royen | G9328: Zapota | H9328: - | I9328: - | J9328: Especial | K9328: - | L9328: Sapotaceae | M9328: 290 | N9328: 103 | O9328: 103
A9329: 290104100 | B9329: Micropholis sp. | C9329: Sapotaceae | D9329: Micropholis | E9329: sp. | F9329: - | G9329: Caimo | Cafeto | H9329: - | I9329: - | J9329: Otras | K9329: - | L9329: Sapotaceae | M9329: 290 | N9329: 104 | O9329: 100
A9330: 290104101 | B9330: Micropholis acutangula (Ducke) Eyma | C9330: Sapotaceae | D9330: Micropholis | E9330: acutangula | F9330: (Ducke) Eyma | G9330: - | H9330: - | I9330: - | J9330: Otras | K9330: - | L9330: Sapotaceae | M9330: 290 | N9330: 104 | O9330: 101
A9331: 290104102 | B9331: Micropholis brochidodroma T.D.Penn. | C9331: Sapotaceae | D9331: Micropholis | E9331: brochidodroma | F9331: T.D.Penn. | G9331: - | H9331: - | I9331: - | J9331: Otras | K9331: - | L9331: Sapotaceae | M9331: 290 | N9331: 104 | O9331: 102
A9332: 290104103 | B9332: Micropholis casiquiarensis Aubrév. | C9332: Sapotaceae | D9332: Micropholis | E9332: casiquiarensis | F9332: Aubrév. | G9332: - | H9332: - | I9332: - | J9332: Otras | K9332: - | L9332: Sapotaceae | M9332: 290 | N9332: 104 | O9332: 103
A9333: 290104104 | B9333: Micropholis crotonoides (Pierre) Pierre | C9333: Sapotaceae | D9333: Micropholis | E9333: crotonoides | F9333: (Pierre) Pierre | G9333: - | H9333: - | I9333: - | J9333: Otras | K9333: - | L9333: Sapotaceae | M9333: 290 | N9333: 104 | O9333: 104
A9334: 290104105 | B9334: Micropholis cylindrocarpa (Poepp.) Pierre | C9334: Sapotaceae | D9334: Micropholis | E9334: cylindrocarpa | F9334: (Poepp.) Pierre | G9334: - | H9334: - | I9334: - | J9334: Otras | K9334: - | L9334: Sapotaceae | M9334: 290 | N9334: 104 | O9334: 105
A9335: 290104106 | B9335: Micropholis egensis (A.DC.) Pierre | C9335: Sapotaceae | D9335: Micropholis | E9335: egensis | F9335: (A.DC.) Pierre | G9335: - | H9335: - | I9335: - | J9335: Otras | K9335: - | L9335: Sapotaceae | M9335: 290 | N9335: 104 | O9335: 106
...

Sheet Regis_Datos_Frutos_Semill_Palma
F2: Formato para presentación de Informe de Censo o Inventario para Manejo Sostenible de Especies con Protocolo
F3: Corporación para el Desarrollo Sostenible del sur de la Amazonia
F4: Plantilla para el Registro de Datos de Campo de PFNM (frutos o semillas) a aprovechar en Palmas
F5: Código: F-LAR-072 | H5: Versión: 2.0 | K5: Fecha: 08/05/2025
D7: Método de muestreo de individuos a aprovechar: | G7: Censo | I7: Inventario Estadistico | L7: Area de Muestreo No. | O7: Forma | Q7: Largo (m) | S7: Ancho (m) | U7: Radio (m) | W7: Area (m2)
D8: Tamaño del predio (ha): | F8: Tamaño de la UMF (ha): | H8: No. de individuos/ha (seleccione si o no, según corresponda) | J8: Menor a 100 Individuos /ha | L8: 100 o Más Individuos /ha | N8: % muestreo con respecto a la UMF (depende del número de individuos y del área de la UMF) | R8: Intensidad del inventario (ha) Este valor se calcula automáticamente | U8: =G8*Q8 -> 0 | V8: Número de indivuos en el área de muestreo
D9: Diseño de muestreo (seleccione si o no en el métodolo que aplique): | G9: Aleatorio | I9: Estratificado | K9: Sistemático | N9: Responsable del inventario: | S9: Fecha del censo, inventario o muestreo: | V9: Cantidad del PFNM en la parcela de muestreo
D11: Información de los individuos objeto de manejo sostenible | N11: Número de racimos | T11: Cantidad de racimos a aprovechar en el individuo evaluado | U11: Peso de un racimo completo (frutos y raquis) en Kg | V11: Cantidad aproximada de frutos o semillas por cada racimo | W11: Peso promedio de un fruto o la semilla con pulpa (gramos) | X11: Peso o Cantidad del PFNM (frutos o semillas) esperado por individuo (kg) | Y11: El individuo reune condiciones apropiadas para el aprovechamiento? Si/No | Z11: Observaciones sobre el individuo
B12: ID | C12: Orden | D12: ID-reg | E12: Nombre común | F12: Nombre científico | G12: Circunferencia a la Altura del Pecho (CAP) del individuo (cm) | H12: Diamentro a la Altura del Pecho - DAP (m) | I12: Altura total de la palma (m) | J12: Altura del tallo de la palma (m) | K12: Estado fisico del individuo | L12: Estado sanitario del individuo | M12: Sin evidencia reproductiva (Sin racimos) | N12: En capuchon | O12: Con inflorescencia | P12: Con frutos verdes | Q12: Con frutos maduros | R12: Senescentes | S12: Proyectados
F13: =VLOOKUP(E13,[1]Cod_spp!A:G,2,0) -> #N/A | H13: =(G13/3.1416)/100 -> 0 | T13: =(N13+O13+P13+R13+Q13+S13) -> 0 | X13: =(T13*V13*W13/1000) -> 0
F14: =VLOOKUP(E14,[1]Cod_spp!A:G,2,0) -> #N/A | H14: =(G14/3.1416)/100 -> 0 | T14: =(N14+O14+P14+R14+Q14+S14) -> 0 | X14: =(T14*V14*W14/1000) -> 0
F15: =VLOOKUP(E15,[1]Cod_spp!A:G,2,0) -> #N/A | H15: =(G15/3.1416)/100 -> 0 | T15: =(N15+O15+P15+R15+Q15+S15) -> 0 | X15: =(T15*V15*W15/1000) -> 0
F16: =VLOOKUP(E16,[1]Cod_spp!A:G,2,0) -> #N/A | H16: =(G16/3.1416)/100 -> 0 | T16: =(N16+O16+P16+R16+Q16+S16) -> 0 | X16: =(T16*V16*W16/1000) -> 0
F17: =VLOOKUP(E17,[1]Cod_spp!A:G,2,0) -> #N/A | H17: =(G17/3.1416)/100 -> 0 | T17: =(N17+O17+P17+R17+Q17+S17) -> 0 | X17: =(T17*V17*W17/1000) -> 0
F18: =VLOOKUP(E18,[1]Cod_spp!A:G,2,0) -> #N/A | H18: =(G18/3.1416)/100 -> 0 | T18: =(N18+O18+P18+R18+Q18+S18) -> 0 | X18: =(T18*V18*W18/1000) -> 0
F19: =VLOOKUP(E19,[1]Cod_spp!A:G,2,0) -> #N/A | H19: =(G19/3.1416)/100 -> 0 | T19: =(N19+O19+P19+R19+Q19+S19) -> 0 | X19: =(T19*V19*W19/1000) -> 0
F20: =VLOOKUP(D20,[1]Cod_spp!A:G,2,0) -> #N/A | H20: =(G20/3.1416)/100 -> 0 | T20: =(N20+O20+P20+R20+Q20+S20) -> 0 | X20: =(T20*V20*W20/1000) -> 0
F21: =VLOOKUP(D21,[1]Cod_spp!A:G,2,0) -> #N/A | H21: =(G21/3.1416)/100 -> 0 | T21: =(N21+O21+P21+R21+Q21+S21) -> 0 | X21: =(T21*V21*W21/1000) -> 0
F22: =VLOOKUP(D22,[1]Cod_spp!A:G,2,0) -> #N/A | H22: =(G22/3.1416)/100 -> 0 | T22: =(N22+O22+P22+R22+Q22+S22) -> 0 | X22: =(T22*V22*W22/1000) -> 0
F23: =VLOOKUP(D23,[1]Cod_spp!A:G,2,0) -> #N/A | H23: =(G23/3.1416)/100 -> 0 | T23: =(N23+O23+P23+R23+Q23+S23) -> 0 | X23: =(T23*V23*W23/1000) -> 0
F24: =VLOOKUP(D24,[1]Cod_spp!A:G,2,0) -> #N/A | H24: =(G24/3.1416)/100 -> 0 | T24: =(N24+O24+P24+R24+Q24+S24) -> 0 | X24: =(T24*V24*W24/1000) -> 0
F25: =VLOOKUP(D25,[1]Cod_spp!A:G,2,0) -> #N/A | H25: =(G25/3.1416)/100 -> 0 | T25: =(N25+O25+P25+R25+Q25+S25) -> 0 | X25: =(T25*V25*W25/1000) -> 0
F26: =VLOOKUP(D26,[1]Cod_spp!A:G,2,0) -> #N/A | H26: =(G26/3.1416)/100 -> 0 | T26: =(N26+O26+P26+R26+Q26+S26) -> 0 | X26: =(T26*V26*W26/1000) -> 0
F27: =VLOOKUP(D27,[1]Cod_spp!A:G,2,0) -> #N/A | H27: =(G27/3.1416)/100 -> 0 | T27: =(N27+O27+P27+R27+Q27+S27) -> 0 | X27: =(T27*V27*W27/1000) -> 0
F28: =VLOOKUP(D28,[1]Cod_spp!A:G,2,0) -> #N/A | H28: =(G28/3.1416)/100 -> 0 | T28: =(N28+O28+P28+R28+Q28+S28) -> 0 | X28: =(T28*V28*W28/1000) -> 0
F29: =VLOOKUP(D29,[1]Cod_spp!A:G,2,0) -> #N/A | H29: =(G29/3.1416)/100 -> 0 | T29: =(N29+O29+P29+R29+Q29+S29) -> 0 | X29: =(T29*V29*W29/1000) -> 0
F30: =VLOOKUP(D30,[1]Cod_spp!A:G,2,0) -> #N/A | H30: =(G30/3.1416)/100 -> 0 | T30: =(N30+O30+P30+R30+Q30+S30) -> 0 | X30: =(T30*V30*W30/1000) -> 0
F31: =VLOOKUP(D31,[1]Cod_spp!A:G,2,0) -> #N/A | H31: =(G31/3.1416)/100 -> 0 | T31: =(N31+O31+P31+R31+Q31+S31) -> 0 | X31: =(T31*V31*W31/1000) -> 0
... F50: =VLOOKUP(D50,[1]Cod_spp!A:G,2,0) -> #N/A | H50: =(G50/3.1416)/100 -> 0 | T50: =(N50+O50+P50+R50+Q50+S50) -> 0 | X50: =(T50*V50*W50/1000) -> 0

Sheet Datos_Pción_Racimos_Frutos_Palm
A1: Especie | B1: Número de racimos/palma Min-Max | C1: No. Racimos promedio/ palma | D1: Número de frutos mínimo-máximo/ racimo | E1: Número promedio de frutos/ racimo | F1: Número promedio de semillas/ racimo | G1: Peso promedio de un racimo (Kg) | H1: Peso promedio de un fruto (g) | I1: Peso promedio de una semilla (g) | J1: Cantidad de frutos por Kg | K1: % máximo de aprovechamiento | L1: % de palmas remanentes | M1: Carácteristicas de individuos potencialmente cosechables
A2: Asaí (Euterpe precatoria) | B2: 1 a 11 | C2: 2.5 | D2: 336 a 7.689 | E2: 2391 | F2: 2391 | G2: 5,9 kg ± 3,5 kg | H2: 1.83 | I2: 1.56 | J2: 546.44 | K2: 0.72 | L2: 0.28 | M2: Altura total mínima de 10 m de individuos en hembra, cuando no muestren evidencias reproductivas.
A3: Canangucha (Mauritia flexuosa) | B3: 1 a 13 | C3: 4 | D3: 134 a 1.267 | E3: 557 | F3: 557 | G3: 22,26 kg ± 16,6 kg | H3: 54.5 | I3: 28.2 | J3: 18.35 | K3: 0.67 | L3: 0.33 | M3: Altura total mínima de 7 m de individuos en hembra, cuando no muestren evidencias reproductivas.
A4: Milpesos (Oenocarpus bataua) | B4: 1 a 14 | C4: 3.3 | D4: 437 a 6.600 | E4: 2061 | F4: 2061 | G4: 20,33 kg ± 11,14 kg | H4: 12.6 | I4: 7.94 | J4: 79.36 | K4: 0.72 | L4: 0.28 | M4: Altura total mínima de 7 m de individuos en hembra, cuando no muestren evidencias reproductivas.
A5: Chontaduro (Bactris gasipaes) | B5: 1 a 13 | C5: 6 | D5: 11 a 250 | E5: 81 | F5: 81 | G5: 4,8 kg ± 2,5 kg | H5: 59.2 | I5: 4.6 | J5: 16.89 | K5: 0.64 | L5: 0.36 | M5: Altura total mínima de 10 m de individuos en hembra, cuando no muestren evidencias reproductivas.
A6: Chambira (Astrocaryum chambira) | B6: 1 a 13 | C6: 3 | D6: 80 a 520 | E6: 192 | F6: 192 | G6: 14,77 kg ± 6,1 kg | H6: 84.6 | I6: 30 | J6: 11.82 | K6: 0.63 | L6: 0.37 | M6: En zonas de cobertura boscosa o al interior del bosque se registrarán todas las palmas que midan 10 metros o más de altura total. En zonas de vegetación secundaria (rastrojos bajos/zonas abiertas) se registrarán todas las palmas que midan desde 2,5 metros de altura total.

Sheet Datos_Pción_Frutos_Semill_FyF
A1: No. | B1: Nombre de la especie | C1: Número promedio de frutos por árbol | D1: Rango frutos Min-Max | E1: Número de frutos por m3 de copa | F1: Cantidad promedia de semillas por fruto | G1: Rango de semillas por fruto Min-Max | H1: Número promedio de semillas por árbol | I1: Rango de semillas Min-Max | J1: Número de semillas por m3 de copa | K1: Peso promedio de un fruto (gramos) | L1: Peso promedio de una semilla (gramos) | M1: Cantidad promedia de frutos /kilogramo | N1: Cantidad promedia de semillas/kilogramo | O1: % máximo de aprovechamiento | P1: % de frutos/semilas a conservar
A2: 1 | B2: Achapo (Cedrelinga cateniformis) | C2: 2782 | D2: 512 a 6.528 | E2: 0.0414 | F2: 4 | G2: 2 a 15 | H2: 12749 | I2: 1.024 a 26.880 | J2: 0.24 | K2: 11.82 | L2: 1.33 | M2: 84.61 | N2: 754.72 | O2: 0.64 | P2: 0.36
A3: 2 | B3: Achiote (Bixa orellana L.) | C3: 309 | D3: 10 a 1.720 | E3: 12.45 | F3: 47 | G3: 15 a 432 | H3: 15067 | I3: 488 a 83.993 | J3: 607.75 | K3: 11.38 | L3: 2.55 | M3: 87.87 | N3: 392.16 | O3: 0.74 | P3: 0.26
A4: 3 | B4: Algarrobo (Hymenaea oblongifolia) | C4: 1296 | D4: 200 a 4.320 | E4: 0.24 | F4: 1 | G4: 1 a 3 | H4: 1457 | I4: 200 a 4.320 | J4: 0.27 | K4: 6.63 | L4: 2.39 | M4: 151 | N4: 418 | O4: 0.62 | P4: 0.38
A5: 4 | B5: Amarillo medio comino (Ocotea aciphylla) | C5: 12768 | D5: 5.568 a 19.968 | E5: 4.88 | F5: 1 | G5: 1 | H5: 12768 | I5: 5.568 a 19.968 | J5: 4.88 | K5: 1.38 | L5: 0.48 | M5: 725 | N5: 2083 | O5: 0.7 | P5: 0.3
A6: 5 | B6: Amarillo (Nectandra reticulata) | C6: 6261 | D6: 1.024 a 34.944 | E6: 1.43 | F6: 1 | G6: 1 | H6: 4654 | I6: 1.152 a 18.773 | J6: 1.22 | K6: 1.08 | L6: 0.65 | M6: 926 | N6: 1538 | O6: 0.66 | P6: 0.34
A7: 6 | B7: Anón amazónico (Annona mucosa) | C7: 64 | D7: 11 a 576 | E7: 0.12 | F7: 51 | G7: 15 a 126 | H7: 4264 | I7: 360 a 26.650 | J7: 1.12 | K7: 369.59 | L7: 0.62 | M7: 3 | N7: 1616 | O7: 0.66 | P7: 0.34
A8: 7 | B8: Arazá (Eugenia stipitata) | C8: 194 | D8: 48 a 816 | E8: 4.3134 | F8: 11 | G8: 7 a 15 | H8: 1909 | I8: 336 a 4.800 | J8: 58.05 | K8: 107.57 | L8: 1.3 | M8: 9 | N8: 769 | O8: 0.63 | P8: 0.37
A9: 8 | B9: Arenillo (Erisma uncinatum) | C9: 3830 | D9: 896 a 7.680 | E9: 0.7452 | F9: 1 | G9: 1 | H9: 3060 | I9: 1.184 a 7.680 | J9: 0.53 | K9: 2.15 | L9: 0.63 | M9: 465 | N9: 1587 | O9: 0.64 | P9: 0.36
A10: 9 | B10: Arracacho (Osteophloeum platyspermum) | C10: 853 | D10: 267 - 1.600 | E10: 0.45 | F10: 1 | G10: 1 | H10: 853 | I10: 267 - 1.600 | J10: 0.45 | K10: 16.93 | L10: 4.58 | M10: 59 | N10: 218 | O10: 0.54 | P10: 0.46
A11: 10 | B11: Balso (Ochroma pyramidale) | C11: 322 | D11: 76 a 1.536 | E11: 0.13 | F11: 710 | G11: 47 a 1.864 | H11: 193530 | I11: 2.816 a 1.191.936 | J11: 96.49 | K11: 43.6 | L11: 0.008 | M11: 23 | N11: 125000 | O11: 0.77 | P11: 0.23
A12: 11 | B12: Barbasco (Minquartia guianensis) | C12: 1003 | D12: 572 a 1.520 | E12: 0.7695 | F12: 1 | G12: 1 | H12: 1020 | I12: 680 a 1.360 | J12: 0.74 | K12: 5 | L12: 3 | M12: 200 | N12: 333 | O12: 0.6 | P12: 0.4
A13: 12 | B13: Bilibil (Guarea guidonia) | C13: 3482 | D13: 1.024 a 8.960 | E13: 2.27 | F13: 4 | G13: 3 a 4 | H13: 14602 | I13: 3.744 a 30.720 | J13: 5.2 | K13: 3.82 | L13: 0.46 | M13: 261.78 | N13: 2174 | O13: 0.7 | P13: 0.3
A14: 13 | B14: Cacao maraco (Theobroma bicolor) | C14: 24 | D14: 2 a 384 | E14: 0.17 | F14: 40 | G14: 30 a 51 | H14: 1944 | I14: 312 a 14.796 | J14: 18.62 | K14: 1429.78 | L14: 6.75 | M14: 0.69 | N14: 148 | O14: 0.69 | P14: 0.31
A15: 14 | B15: Cachimbo (Erythrina fusca) | C15: 6167 | D15: 3.008 a 11.520 | E15: 2.3663 | F15: 7 | G15: 2 a 13 | H15: 40947 | I15: 15.040 a 86.528 | J15: 13.7 | K15: 6.98 | L15: 0.47 | M15: 143 | N15: 2128 | O15: 0.87 | P15: 0.13
A16: 15 | B16: Cachimbo (Erythrina poeppigian) | C16: 4898 | D16: 1,600 a 8.960 | E16: 1.0694 | F16: 2 | G16: 2 | H16: 9797 | I16: 3.200 a 17.920 | J16: 2.14 | K16: 0.98 | L16: 0.25 | M16: 1020 | N16: 4000 | O16: 0.84 | P16: 0.16
A17: 16 | B17: Caimitillo (Pouteria sp.) | C17: 617 | D17: 28 a 1.152 | E17: 0.39 | F17: 1 | G17: 1 | H17: 617 | I17: 672 a 1.152 | J17: 0.39 | K17: 21 | L17: 2 | M17: 48 | N17: 500 | O17: 0.53 | P17: 0.47
A18: 17 | B18: Caimo (frutal) (Pouteria caimito) | C18: 142 | D18: 20 a 597 | E18: 1.9244 | F18: 2 | G18: 1 a 4 | H18: 351 | I18: 40 a 768 | J18: 3.44 | K18: 142.51 | L18: 4.78 | M18: 7 | N18: 209 | O18: 0.59 | P18: 0.41
A19: 18 | B19: Canalete (Jacaranda copaia) | C19: 1088 | D19: 150 a 7.744 | E19: 1029 | F19: 71 | G19: 52 a 307 | H19: 67029 | I19: 54.912 a 687.680 | J19: 207 | K19: 15 | L19: 0.0047 | M19: 67 | N19: 212766 | O19: 0.72 | P19: 0.28
A20: 19 | B20: Canelo de los Andaquíes (Mespilodaphne quixos) | C20: 494 | D20: 240 a 960 | E20: 0.34 | F20: 1 | G20: 1 | H20: 494 | I20: 240 a 960 | J20: 0.34 | K20: 18 | L20: 9.67 | M20: 56 | N20: 103 | O20: 0.53 | P20: 0.47
A21: 20 | B21: Capirón de vega (Calycophyllum spruceanum) | C21: 49605 | D21: 5.344 a 385.506 | E21: 35.6 | F21: 2 | G21: 1 a 2 | H21: 159575 | I21: 18.048 a 771.012 | J21: 129.4 | K21: 0.04 | L21: 0.0036 | M21: 22305 | N21: 275634 | O21: 0.62 | P21: 0.38
A22: 21 | B22: Caracolí (Anacardium excelsum) | C22: 971 | D22: 256 a 2.112 | E22: 0.1 | F22: 1 | G22: 1 | H22: 1415 | I22: 256 a 2.112 | J22: 0.13 | K22: 18 | L22: 4.95 | M22: 55 | N22: 202 | O22: 0.61 | P22: 0.39
A23: 22 | B23: Caraño (Trattinnickia aspera) | C23: 3203 | D23: 1.067 a 9.308 | E23: 1.1539 | F23: 1 | G23: 1 | H23: 2936 | I23: 1.067 a 9.216 | J23: 0.58 | K23: 1.01 | L23: 0.43 | M23: 1000 | N23: 2325 | O23: 0.77 | P23: 0.23
A24: 23 | B24: Carguero (Couratari guianensis) | C24: 875 | D24: 683 a 981 | E24: 0.032 | F24: 8 | G24: 8 a 26 | H24: 6997 | I24: 5.464 a 7.848 | J24: 0.26 | K24: 18.66 | L24: 0.13 | M24: =1000/K24 -> 53.590568 | N24: 7.140 a 8.330 | O24: 0.7 | P24: 0.3
A25: 24 | B25: Carrecillo (Pochota fendleri) | C25: 196 | D25: 128 a 260 | E25: 0.033 | F25: 37 | G25: 10 a 140 | H25: 2340 | I25: 1.212 a 3.520 | J25: 0.41 | K25: 7.97 | L25: 0.0443 | M25: 125 | N25: 32792 | O25: 0.63 | P25: 0.37
A26: 25 | B26: Casco de vaca rojo (Calliandra trinervia) | C26: 699 | D26: 64 a 3.136 | E26: 0.4305 | F26: 5 | G26: 3 a 8 | H26: 3842 | I26: 256 a 18.816 | J26: 2.65 | K26: 20.54 | L26: 0.94 | M26: 48.7 | N26: 1067 | O26: 0.65 | P26: 0.35
A27: 26 | B27: Castaña del Brasil (Bertholletia excelsa) | C27: 98 | D27: 8 a 256 | E27: 0.0152 | F27: 16 | G27: 8 a 26 | H27: 1574 | I27: 272 a 5.280 | J27: 0.22 | K27: 1090 | L27: 13.62 | M27: 0.91 | N27: 73 | O27: 0.74 | P27: 0.26
A28: 27 | B28: Cedro (Cedrela odorata L.) | C28: 1669 | D28: 192 a 13.440 | E28: 0.9588 | F28: 40 | G28: 16 a 65 | H28: 81106 | I28: 3.840 a 698.880 | J28: 53.77 | K28: 6.97 | L28: 0.0263 | M28: 143 | N28: 38022 | O28: 0.65 | P28: 0.35
A29: 28 | B29: Ceiba (Ceiba pentandra) | C29: 1125 | D29: 300 a 2.597 | E29: 0.0183 | F29: 154 | G29: 71 a 204 | H29: 168612 | I29: 46.200 a 308.000 | J29: 2.74 | K29: 194.4 | L29: 0.08 | M29: 5 | N29: 17107 | O29: 0.66 | P29: 0.34
A30: 29 | B30: Chíparo (Zygia longifolia) | C30: 4827 | D30: 512 a 17.088 | E30: 1.44 | F30: 12 | G30: 7 a 16 | H30: 61998 | I30: 4.096 a 219.024 | J30: 16.8 | K30: 10.88 | L30: 0.75 | M30: 92 | N30: 1332 | O30: 0.7 | P30: 0.3
A31: 30 | B31: Chocho (Ormosia nobilis) | C31: 3531 | D31: 139 a 16.000 | E31: 1.03 | F31: 2 | G31: 1 a 4 | H31: 6103 | I31: 278 a 27.072 | J31: 2 | K31: 2.86 | L31: 0.81 | M31: 350 | N31: 1239 | O31: 0.75 | P31: 0.25
A32: 31 | B32: Cobre (Andira inermis) | C32: 2252 | D32: 80 a 10.560 | E32: 1 | F32: 1 | G32: 1 | H32: 2252 | I32: 80 a 10.560 | J32: 1 | K32: 18.57 | L32: 7.22 | M32: 54 | N32: 139 | O32: 0.68 | P32: 0.32
A33: 32 | B33: Copoazú (Theobroma grandiflorum) | C33: 54 | D33: 4 a 384 | E33: 0.18 | F33: 36 | G33: 10 a 62 | H33: 1143 | I33: 120 a 5.376 | J33: 1.23 | K33: 1280.67 | L33: 8.47 | M33: 0.67 | N33: 118 | O33: 0.77 | P33: 0.23
A34: 33 | B34: Costillo (Aspidosperma excelsum) | C34: 1050 | D34: 96 a 1.608 | E34: 0.2469 | F34: 15 | G34: 10 a 28 | H34: 13933 | I34: 512 a 21.504 | J34: 4.51 | K34: 45.9 | L34: 0.57 | M34: 22 | N34: 1754 | O34: 0.66 | P34: 0.34
A35: 34 | B35: Costillo (Aspidosperma rigidum) | C35: 186 | D35: 100 a 320 | E35: 0.1431 | F35: 12 | G35: 9 a 16 | H35: 2225 | I35: 1.260 a 4.096 | J35: 0.52 | K35: 25.87 | L35: 0.15 | M35: 37 | N35: 6666 | O35: 0.66 | P35: 0.34
A36: 35 | B36: Cucharo (Myrsine guianensis) | C36: 86510 | D36: 4.600 a 355.250 | E36: 115.62 | F36: 1 | G36: 1 | H36: 118245 | I36: 8.000 a 355.250 | J36: 163.83 | K36: 0.0638 | L36: 0.0473 | M36: 15674 | N36: 21142 | O36: 0.68 | P36: 0.32
A37: 36 | B37: Fono (Eschweilera sp.) | C37: 656 | D37: 8 a 1.536 | E37: 0.3137 | F37: 3 | G37: 1 a 4 | H37: 2007 | I37: 8 a 4.032 | J37: 0.5 | K37: 144 | L37: 10 | M37: 7 | N37: 100 | O37: 0.64 | P37: 0.36
A38: 37 | B38: Fono (Eschweilera coriacea) | C38: 801 | D38: 240 a 1.536 | E38: 0.1586 | F38: 3 | G38: 2 a 4 | H38: 2301 | I38: 720 a 4.032 | J38: 0.39 | K38: 162.96 | L38: 9.45 | M38: 6 | N38: 106 | O38: 0.64 | P38: 0.36
A39: 38 | B39: Fresno (Tapirira guianensis) | C39: 1942 | D39: 528 a 4.992 | E39: 0.2557 | F39: 1 | G39: 1 | H39: 1918 | I39: 528 a 4.736 | J39: 0.22 | K39: 7.37 | L39: 0.95 | M39: 136 | N39: 1051 | O39: 0.7 | P39: 0.3
A40: 39 | B40: Golondrino (Oxandra xylopioides) | C40: 640 | D40: 496 a 936 | E40: 3.78 | F40: 1 | G40: 1 | H40: 640 | I40: 496 a 936 | J40: 3.78 | K40: 2.33 | L40: 0.54 | M40: 430 | N40: 1852 | O40: 0.57 | P40: 0.43
A41: 40 | B41: Gomo (Vochysia braceliniae) | C41: 3968 | D41: 2.048 a 6.752 | E41: 1.0065 | F41: 3 | G41: 3 | H41: 13344 | I41: 6.912 a 20.256 | J41: 1.76 | K41: 3.61 | L41: 0.124 | M41: 277 | N41: 4963 | O41: 0.56 | P41: 0.44
A42: 41 | B42: Gomo (Vochysia sp) | C42: 4453 | D42: 2.048 a 6.752 | E42: 0.8565 | F42: 3 | G42: 3 | H42: 14074 | I42: 6.912 a 20.256 | J42: 1.7 | K42: 3.39 | L42: 0.143 | M42: 295 | N42: 6993 | O42: 0.56 | P42: 0.44
A43: 42 | B43: Granadillo (Platymiscium pinnatum) | C43: 6148 | D43: 1.000 a 23.040 | E43: 3.74 | F43: 1 | G43: 1 | H43: 6148 | I43: 1.000 a 23.040 | J43: 3.74 | K43: 0.88 | L43: 0.34 | M43: 1136 | N43: 1941 | O43: 0.66 | P43: 0.34
A44: 43 | B44: Guamo diablo (Tachigali sp.) | C44: 5979 | D44: 896 a 13.824 | E44: 0.3717 | F44: 1 | G44: 1 | H44: 5979 | I44: 896 a 13.824 | J44: 0.37 | K44: 9.16 | L44: 5.57 | M44: 109 | N44: 180 | O44: 0.66 | P44: 0.34
A45: 44 | B45: Guamo (Inga edulis Mart.) | C45: 232 | D45: 16 a 2004 | E45: 0.1594 | F45: 14 | G45: 4 a 27 | H45: 3725 | I45: 80 a 30.080 | J45: 2.71 | K45: 300.62 | L45: 3.17 | M45: 3 | N45: 316 | O45: 0.65 | P45: 0.35
A46: 45 | B46: Guarango (Parkia sp.) | C46: 1164 | D46: 64 a 9.984 | E46: 0.1207 | F46: 15 | G46: 7 a 39 | H46: 26077 | I46: 2.728 a 389.376 | J46: 3.86 | K46: 91.5 | L46: 2.05 | M46: 11 | N46: 488 | O46: 0.6 | P46: 0.4
A47: 46 | B47: Guarango (Parkia multijuga) | C47: 780 | D47: 248 a 1.920 | E47: 0.0441 | F47: 13 | G47: 7 a 18 | H47: 9822 | I47: 2.728 a 26.880 | J47: 0.56 | K47: 96.27 | L47: 1.87 | M47: 10 | N47: 535 | O47: 0.64 | P47: 0.36
A48: 47 | B48: Guarango (Parkia nitida) | C48: 1290 | D48: 64 a 3.200 | E48: 0.1079 | F48: 14 | G48: 12 a 17 | H48: 23496 | I48: 3.168 a 44.800 | J48: 35 | K48: 96 | L48: 2.55 | M48: 10 | N48: 392 | O48: 0.65 | P48: 0.35
A49: 48 | B49: Guarango (Parkia velutina) | C49: 2928 | D49: 240 a 9.984 | E49: 0.5677 | F49: 27 | G49: 15 a 39 | H49: 160368 | I49: 3.600 a 389.376 | J49: 32.87 | K49: 55 | L49: 2.73 | M49: 18 | N49: 366 | O49: 0.61 | P49: 0.39
A50: 49 | B50: Guayacán amarillo (Handroanthus chrysanthus) | C50: 185 | D50: 177 a 192 | E50: 0.08 | F50: 308 | G50: 91 a 491 | H50: 56938.89 | I50: 54.678 a 59.200 | J50: 24.66 | K50: 113 | L50: 0.08 | M50: 8.84 | N50: 12500 | O50: 0.7 | P50: 0.3
A51: 50 | B51: Higuerón (Ficus insipida Willd) | C51: 2466 | D51: 728 a 7.040 | E51: 0.089 | F51: 313 | G51: 180 a 478 | H51: 865580 | I51: 284.220 a 1.880.064 | J51: 16.93 | K51: 7.92 | L51: 0.0036 | M51: 126 | N51: 277778 | O51: 0.67 | P51: 0.33
A52: 51 | B52: Inchi (Caryodendron orinocense) | C52: 1310 | D52: 116 a 5.250 | E52: 0.0874 | F52: 3 | G52: 1 a 3 | H52: 4016 | I52: 348 a 15.750 | J52: 0.26 | K52: 42 | L52: 4.6 | M52: 24 | N52: 218 | O52: 0.75 | P52: 0.25
A53: 52 | B53: Juansoco (Couma macrocarpa) | C53: 817 | D53: 220 a 3.000 | E53: 0.24 | F53: 12 | G53: 1 a 48 | H53: 5840 | I53: 2.304 a 12.800 | J53: 2.5 | K53: 59.32 | L53: 1.53 | M53: 17 | N53: 654 | O53: 0.57 | P53: 0.43
A54: 53 | B54: Lacre (Vismia baccifera) | C54: 3593 | D54: 48 a 15.884 | E54: 3.88 | F54: 132 | G54: 40 a 305 | H54: 376930 | I54: 3,024 a 1.196.800 | J54: 426.55 | K54: 1.73 | L54: 0.0014 | M54: 578 | N54: 714286 | O54: 0.72 | P54: 0.28
A55: 54 | B55: Madroño (Garcinia madruno) | C55: 651 | D55: 16 a 2.880 | E55: 0.52 | F55: 4 | G55: 2 a 5 | H55: 2229 | I55: 192 a 8.640 | J55: 1.74 | K55: 81.49 | L55: 6.69 | M55: 12 | N55: 149 | O55: 0.61 | P55: 0.39
A56: 55 | B56: Madroño (Garcinia macrophylla) | C56: 1074 | D56: 30 a 4.869 | E56: 1.35 | F56: 3 | G56: 2 a 4 | H56: 3704 | I56: 90 a 18.132 | J56: 6.57 | K56: 74.68 | L56: 5.2 | M56: 13 | N56: 192 | O56: 0.61 | P56: 0.39
A57: 56 | B57: Maní (Caryocar glabrum) | C57: 152 | D57: 24 a 448 | E57: 0.0426 | F57: 1 | G57: 1 | H57: 152 | I57: 24 a 448 | J57: 0.04 | K57: 139.67 | L57: 24.56 | M57: 7 | N57: 41 | O57: 0.54 | P57: 0.46
A58: 57 | B58: Mano de oso (Didymopanax morototoni) | C58: 37853 | D58: 9.296 a 68.800 | E58: 37.47 | F58: 2 | G58: 2 | H58: 83628 | I58: 18.592 a 135.680 | J58: 71.56 | K58: 0.17 | L58: 0.0508 | M58: 5882 | N58: 19671.83 | O58: 0.66 | P58: 0.34
A59: 58 | B59: Marañón (Anacardium occidentale) | C59: 160 | D59: 4 a 2.128 | E59: 1.2201 | F59: 3 | G59: 1 a 35 | H59: 401 | I59: 14 a 3.500 | J59: 1.84 | K59: 58.5 | L59: 5.63 | M59: 17 | N59: 178 | O59: 0.65 | P59: 0.35
A60: 59 | B60: Morochillo (Miconia sp) | C60: 25518 | D60: 5.480 a 60.000 | E60: 109 | F60: 27 | G60: 12 a 85 | H60: 454798 | I60: 116.032 a 837.760 | J60: 1613 | K60: 0.043 | L60: 0.0044 | M60: 23041 | N60: 227273 | O60: 0.75 | P60: 0.25
A61: 60 | B61: Morochillo (Miconia elata) | C61: 27843 | D61: 8.288 a 51.120 | E61: 180.27 | F61: 14 | G61: 12 a 18 | H61: 382834 | I61: 116.032 a 664.560 | J61: 2474.33 | K61: 0.039 | L61: 0.013 | M61: 25641 | N61: 80000 | O61: 0.75 | P61: 0.25
A62: 61 | B62: Motilon silvestre (Hieronyma alchorneoides) | C62: 34191 | D62: 2.080 a 69.280 | E62: 22.5659 | F62: 1 | G62: 1 | H62: 47905 | I62: 11.616 a 69.280 | J62: 31.76 | K62: 0.0559 | L62: 0.011 | M62: 17889 | N62: 90909 | O62: 0.69 | P62: 0.31
A63: 62 | B63: Nagüí (Guatteria spp) | C63: 4325 | D63: 48 a 11.880 | E63: 1.55 | F63: 1 | G63: 1 | H63: 4896 | I63: 3.008 a 8.960 | J63: 1.44 | K63: 0.31 | L63: 0.14 | M63: 3226 | N63: 7082 | O63: 0.68 | P63: 0.32
A64: 63 | B64: Nagüí (Guatteria scytophylla) | C64: 4504 | D64: 48 a 8.960 | E64: 1.2559 | F64: 1 | G64: 1 | H64: 4504 | I64: 48 a 8.960 | J64: 1.26 | K64: 0.12 | L64: 0.07 | M64: 8333 | N64: 13572 | O64: 0.68 | P64: 0.32
A65: 64 | B65: Nagüí (Guatteria punctata) | C65: 2212 | D65: 56 a 4.350 | E65: 1.1462 | F65: 1 | G65: 1 | H65: 2212 | I65: 56 a 4.350 | J65: 1.15 | K65: 0.31 | L65: 0.14 | M65: 3226 | N65: 7082 | O65: 0.68 | P65: 0.32
A66: 65 | B66: Nagüí (Guatteria ucayalina) | C66: 5061 | D66: 224 a 11.880 | E66: 1.76 | F66: 1 | G66: 1 | H66: 5061 | I66: 224 a 11.880 | J66: 1.76 | K66: 0.41 | L66: 0.18 | M66: 2439 | N66: 5714 | O66: 0.68 | P66: 0.32
A67: 66 | B67: Nogal cafetero (Cordia alliodora) | C67: 19182.043 | D67: 3.200 a 61.440 | E67: 17.032522 | F67: 1 | G67: 1 | H67: 19182.043 | I67: 3.200 - 61.440 | J67: 17.03 | K67: 0.0256 | L67: 0.016 | M67: 39062.5 | N67: 62619.714 | O67: 0.62 | P67: 0.38
A68: 67 | B68: Palocruz (Brownea grandiceps) | C68: 17 | D68: 4 a 38 | E68: 0.0984 | F68: 6 | G68: 1 a 10 | H68: 137 | I68: 4 a 360 | J68: 0.9 | K68: 189.64 | L68: 17.33 | M68: 5 | N68: 58 | O68: 0.6 | P68: 0.4
A69: 68 | B69: Palonegro (Piptocoma discolor) | C69: 180272 | D69: 28.320 a 633.798 | E69: 96.88 | F69: 1 | G69: 1 | H69: 162493 | I69: 28.320 a 633.798 | J69: 94.79 | K69: 0.0034 | L69: 0.0004 | M69: 294118 | N69: 2500000 | O69: 0.68 | P69: 0.32
A70: 69 | B70: Patevaca blanco (Bauhinia tarapotensis) | C70: 328 | D70: 67 a 960 | E70: 0.762 | F70: 10 | G70: 5 a 16 | H70: 2802 | I70: 720 a 7.040 | J70: 5.35 | K70: 20.29 | L70: 0.28 | M70: 49.28 | N70: 3571 | O70: 0.69 | P70: 0.31
A71: 70 | B71: Patevaca (Bauhinia picta) | C71: 737 | D71: 120 a 1.760 | E71: 0.2824 | F71: 7 | G71: 4 a 9 | H71: 5756 | I71: 840 a 10.880 | J71: 2.05 | K71: 10.49 | L71: 0.24 | M71: 95 | N71: 4167 | O71: 0.69 | P71: 0.31
A72: 71 | B72: Peinemono (Apeiba membranacea) | C72: 650 | D72: 104 a 1.584 | E72: 0.2994 | F72: 157 | G72: 36 a 298 | H72: 71176 | I72: 6.720 a 200.704 | J72: 52.15 | K72: 20.46 | L72: 0.0436 | M72: 49 | N72: 22931 | O72: 0.73 | P72: 0.27
A73: 72 | B73: Pino colombiano (Podocarpus sp.) | C73: 2051 | D73: 1.280 a 2.816 | E73: 0.6795 | F73: 2 | G73: 2 | H73: 3392 | I73: 2.560 a 4.224 | J73: 1.11 | K73: 0.8 | L73: 0.12 | M73: 1250 | N73: 8333 | O73: 0.67 | P73: 0.33
A74: 73 | B74: Sangredrago (Croton lechleri) | C74: 11756 | D74: 168 a 56.496 | E74: 7 | F74: 3 | G74: 3 | H74: 31296 | I74: 1.584 a 102.816 | J74: 23 | K74: 0.06 | L74: 0.01 | M74: 16666 | N74: 100000 | O74: 0.77 | P74: 0.23
A75: 74 | B75: Sangretoro (Virola sp.) | C75: 2304 | D75: 32 a 6.624 | E75: 1.0731 | F75: 1 | G75: 1 | H75: 1843 | I75: 128 a 6.000 | J75: 0.71 | K75: 14.51 | L75: 2.64 | M75: 69 | N75: 379 | O75: 0.6 | P75: 0.4
A76: 75 | B76: Sapotolongo (Pachira speciosa) | C76: 140 | D76: 72 a 288 | E76: 0.0805 | F76: 42 | G76: 20 a 70 | H76: 5497 | I76: 1.920 a 11.136 | J76: 3.29 | K76: 1278.67 | L76: 5.97 | M76: 0.78 | N76: 167 | O76: 0.64 | P76: 0.36
A77: 76 | B77: Tara (Simarouba amara) | C77: 8473 | D77: 1.376 a 28.000 | E77: 3.7263 | F77: 1 | G77: 1 | H77: 10161 | I77: 1.376 a 28.000 | J77: 5.08 | K77: 1.89 | L77: 0.7 | M77: 530 | N77: 1428 | O77: 0.79 | P77: 0.21
A78: 77 | B78: Uva caimarona (Pourouma cecropiifolia) | C78: 3617 | D78: 288 a 21.504 | E78: 3.23 | F78: 1 | G78: 1 | H78: 3617 | I78: 288 a 21.504 | J78: 3.66 | K78: 12.95 | L78: 2.44 | M78: 77 | N78: 410 | O78: 0.74 | P78: 0.26
A79: 78 | B79: Yarumo (Cecropia distachya) | C79: 786141 | D79: 331.776 a 1.574.656 | E79: 1631.55 | F79: 1 | G79: 1 | H79: 786141 | I79: 331.776 a 1.574.656 | J79: 1631.55 | K79: 0.0029 | L79: 0.0003 | M79: 344828 | N79: 3333333 | O79: 0.72 | P79: 0.28
A80: 79 | B80: Yarumo (Cecropia putumayonis) | C80: 2108277 | D80: 1.011.600 a 3.929.664 | E80: 1014.97 | F80: 1 | G80: 1 | H80: 2108277 | I80: 1.011.600 a 3.929.664 | J80: 1014.97 | K80: 0.002 | L80: 0.0003 | M80: 500000 | N80: 3333333 | O80: 0.72 | P80: 0.28
A81: 80 | B81: Yarumo (Cecropia sciadophylla) | C81: 1302803 | D81: 500.544 a 2.111.508 | E81: 226.75 | F81: 1 | G81: 1 | H81: 1302803 | I81: 500.544 a 2.111.508 | J81: 226.75 | K81: 0.0021 | L81: 0.00019 | M81: 476190 | N81: 5263158 | O81: 0.72 | P81: 0.28
A82: 81 | B82: Zapote (Matisia cordata) | C82: 404 | D82: 80 a 1.152 | E82: 0.1524 | F82: 5 | G82: 4 a 6 | H82: 1956 | I82: 320 a 4.096 | J82: 0.7 | K82: 535.54 | L82: 13.23 | M82: 1.86 | N82: 75.58 | O82: 0.66 | P82: 0.34

Sheet Observaciones
B2: NOTA FINAL ACLARATORIA
B4: En caso de encontrar inconsistencias en esta plantilla, o si tiene algún comentario que permita mejorar
B5: su contenido, por favor remita sus comentarios al correo electrónico oficial de Corpoamazonia:
B6: correspondencia@corpoamazonia.gov.co
B8: Asunto: ACCION DE MEJORA PLANTILLA F-LAR-072 del Sistema de Gestión de Calidad
B10: De ser posible inserte sus comentarios en la hoja que corresponda y resáltela con un color diferente.
B11: En esta hoja, a continuación especifique la(s) hoja(s) donde insertó sus comentarios, y exprese los comentarios aclaratorios o que considere pertinentes
B13: OBSERVACIONES POR PARTE DEL INTERESADO O USUARIO:
B15: Deje en esta sección sus comentarios; gracias.
